Workbook

Sheet config
A1: key | B1: value | C1: help
A2: url | B2: http://koltsegvetes.terezvaros.hu/ | C2: A weboldal leendő URL-je. Keresőoptimalizálásnál és megosztásnál van szerepe.
A3: modules.income | B3: 1 | C3: Bevételek szakasz megjelenítése? (1 = Igen, 0 = Nem) Ha ki van kapcsolva, akkor a költségvetés bemutatása a kiadásokkal indul. Automatikusan ki lesz kapcsolva, ha nincs bevételi adat.
A4: modules.inex | B4: 1 | C4: Mérleg szakasz megjelenítése? (1 = Igen, 0 = Nem) Automatikusan kikapcsol, ha a "modules.income" ki van kapcsolva.
A5: modules.milestones | B5: 1 | C5: Fejlesztések szakasz megjelenítése? (1 = Igen, 0 = Nem)
A6: modules.pub | B6: 1 | C6: Kiadványos szakasz megjelenítése? (1 = Igen, 0 = Nem)
A7: modules.feedback | B7: 1 | C7: Visszajelzés szakasz/gomb megjelenítése? (1 = Igen, 0 = Nem)
A8: modules.social | B8: 1 | C8: Legyenek megosztás gombok? (1 = Igen, 0 = Nem)
A9: modules.map | B9: 0 | C9: Térkép szakasz megjelenítése? (1 = Igen, 0 = Nem)
A10: modules.timeseries-income | B10: 1 | C10: Idősor szakasz megjelenítése? (1 = Igen, 0 = Nem)
A11: modules.timeseries-expense | B11: 1 | C11: Idősor szakasz megjelenítése? (1 = Igen, 0 = Nem)
A12: modules.order | B12: timeseries-expense,timeseries-income,milestones,expense,income,inex,pub,map,feedback | C12: Modulok sorrendje (alapértelmezett: pub,inex,income,expense,timeseries-income,timeseries-expense,milestones,map,feedback)
A14: defaultYear | B14: 2026 | C14: Alapértelmezettként kiválasztott év.
A15: seo.siteName | B15: Terézváros | C15: Böngészőablak címsorának 2. része. A teljes címsor max. 60 karakter lehet.
A16: seo.pageTitle | B16: Költségvetés | C16: Böngészőablak címsorának 2. része. A teljes címsor max. 60 karakter lehet.
A17: seo.ogTitle | B17: Közérthető költségvetés 2026 | C17: Facebook/Twitter megosztáskor az előnézeti kártya címsora.
A18: seo.description | B18: Mire, miből és mennyit költ Terézváros? | C18: Google találatban, ill. Facebook/Twitter megosztáskor az előnézeti kártyában megjelenő leírás. Max. 160 karakter.
A19: social.text | B19: Terézváros költségvetése | C19: Megosztáskor a Twitter bejegyzés szövege, LinkedIn poszt vagy email tárgya.
A20: city | B20: Terézváros | C20: Felső navigációs sáv bal oldalán megjelenő városnév.
A22: navBar.showBanner | B22: 0 | C22: Banner megjelenítése? (1 = Igen, 0 = Nem)
A23: navBar.welcome | B23: Köszöntő | C23: Köszöntő szakaszra mutató link szövege a felső navigációs sávban.
A24: navBar.inex | B24: Költségvetés | C24: Költségvetés szakaszra mutató link szövege a felső navigációs sávban.
A25: navBar.milestones | B25: Fejlesztések | C25: Fejlesztések szakaszra mutató link szövege a felső navigációs sávban.
A26: navBar.map | B26: Térkép | C26: Térkép szakaszra mutató link szövege a felső navigációs sávban.
A27: navBar.moreInfo | B27: A projektről | C27: További információ ablakot előhívó link szövege a felső navigációs sávban.
A28: navBar.bannerText | B28: Megcsinálnád településednek? [Telepítsd a keretrendszert!](http://github.com/k-monitor/onkormanyzati-koltsegvetes-v2) | C28: Banner szövege. Markdown jelölések használhatóak (pl. formázás, linkek).
A30: search.tooShort | B30: Túl rövid keresőkifejezés! | C30: Kereséskor megjelenő szöveg, ha túl rövid a keresőkifejezés.
A31: search.noResults | B31: Nincs találat. | C31: Kereséskor megjelenő szöveg, ha nincs találat.
A32: search.income | B32: Bevételek | C32: Keresési találatban megjelenő link szövege, mely a Bevételek szakaszra mutat.
A33: search.expense | B33: Kiadások | C33: Keresési találatban megjelenő link szövege, mely a Kiadások szakaszra mutat.
A34: search.milestones | B34: Fejlesztések | C34: Keresési találatban megjelenő link szövege, mely a Fejlesztések szakaszra mutat.
A35: search.econ | B35: közgazdasági kategória | C35: Keresési találatban megjelenő szöveg, ha az adott találat egy közgazdasági kategória.
... A48: welcome.role | B48: Terézváros polgármestere | C48: Köszöntő szakaszt aláíró személy tisztsége.
A50: tutorial.K1107 | C50: Hasábokra von. tutorial lépések így szúrhatók be. A 2. oszlopba kell írni a szöveget.
A52: pub.lead | B52: Mélyebbre ásnának az adatokban? Ha a költségvetési tételekhez kapcsolódó konkrét, teljesült költésekről (szerződésekről, támogatásokról, közbeszerzésekről) tájékozódnának, ezt Terézváros honlapján, a közérdekű adatok között találják meg. Itt olvasható leírás arról is, hogyan lehet információhoz jutni közérdekű adatigénylés formájában. | C52: Kiadvány szakasz szövege
A53: pub.url | B53: https://terezvaros.hu/atlathatosag | C53: Kiadvány szakasz gombja erre az URL-re linkel.
A55: moreInfo.title | B55: A projektről | C55: További információ ablak címsora.
A56: moreInfo.text | B56: A K-Monitor és partnerei által fejlesztett eszköz alkalmas az önkormányzati költségvetések terv- és tényadatainak bemutatására a megrendelő önkormányzat által meghatározott részletezettségű bontásban. Az adatokhoz kapcsolva egyes bevételi és kiadási előirányzatok tartalmának ismertetése is lehetővé válik. Az eszköz példákkal és illusztrációkkal érthetővé, átélhetővé teszi az önkormányzatok szerteágazó feladatait olyan állampolgárok számára is, akik kevés ismerettel rendelkeznek a közpénzügyek területén. A terézvárosi vizualizáció alapjául szolgáló költségvetések táblázatos formában [itt érhetők el](https://terezvaros.hu/atlathatosag/koltsegvetesek). | C56: További információ ablak címsora. Markdown jelölések használhatóak (pl. formázás, linkek).
A58: inex.title | B58: Mérleg | C58: Mérleg szakasz címsora.
A59: inex.subtitle | B59: Terézváros idei költségvetése: | C59: Mérleg ábra fejléce.
A60: inex.expenseNodes | B60: K1,K2,K3,K4,K8,K5,K6,K7 | C60: Mérleg ábra kiadási oldalán szereplő hasábok azonosítói vesszővel elv.
A61: inex.incomeNodes | B61: B1,B2,B3,B5,B4,B6,B7 | C61: Mérleg ábra bevételi oldalán szereplő hasábok azonosítói vesszővel elv.
A62: inex.text | B62: **Segítünk értelmezni!** Az ábra Terézváros önkormányzatának és intézményeinek éves költségvetését mutatja mérlegszerű bontásban. A hasábokra navigálva magyarázatok olvashatóak. A bevételek és kiadások is felbonthatók működési és felhalmozási tételekre. A <span style="background: #61C1D6">működési&nbsp;költségvetés</span> a zavartalan feladatellátást biztosítja, míg a <span style="background: #B56DB6">felhalmozási&nbsp;költségvetés</span> beruházásokhoz, felújításokhoz kapcsolódik, amelyek célja tartós eszközök beszerzése, a tevékenység bővítése, modernizálása. A működési bevételek (törvényben meghatározott állami támogatások, helyi adók, nyújtott szolgáltatások ellenértéke) és kiadások (bérek, rezsiköltségek, nyújtott támogatások) rendszeresen, ciklikusan jelentkeznek. Ezzel szemben a felhalmozási tételek eseti jellegűek. A részben éven belüli, számviteli tételeket tartalmazó <span style="background: #FFD074">finanszírozási&nbsp;költségvetés</span> többlete bevételként jelentkezik, amiből kiadások fedezete biztosítható (pl. korábbi évek maradványa, lejáró betétek). | C62: Mérleg szakasz ábra alatti szövege. Markdown jelölések használhatóak (pl. formázás, linkek).
A64: vis.income | B64: Bevételek | C64: Bevételek szakasz címsora.
A65: vis.incomeText | B65: **Segítünk értelmezni!** A bevételeket közgazdasági bontásban, működési, felhalmozási és finanszírozási jelleg alapján csoportosítjuk. A működési bevételeken belül a központi költségvetésből kapott támogatásokat, a közhatalmi bevételeket (adók, díjak, bírságok), egyéb működési bevételeket (pl. szolgáltatások ellenértéke), és a működésre kapott támogatásokat különítjük el. A felhalmozási bevételek tartalmazzák az önkormányzati vagyon értékesítéséből származó bevételeket. A finanszírozási bevételek között találhatók az előző évi gazdálkodás maradványai. | C65: Bevétel ábra alatti szöveg (opcionális).
A66: vis.expense | B66: Kiadások | C66: Kiadások szakasz címsora.
... A74: map.title | B74: Fejlesztések térképen | C74: Térkép szakasz címsora.
A76: timeseries.func | B76: 0 | C76: Idősor funkcionális oldal megjelenítése? (1 = Igen, 0 = Nem)
A77: timeseries.econ | B77: 1 | C77: Idősor közgazdasági oldal megjelenítése? (1 = Igen, 0 = Nem)
A78: timeseries.years | B78: 2020,2021,2022,2023,2024,2025,2026 | C78: Idősor szűrése a megadott évekre. (pl.: “2020,2021,2022”)
A79: timeseries.kgrOnly | B79: 1 | C79: Közgazdasági idősor korlátozása a KGR lapon megadott rovatkódokra. (1 = Igen, 0 = Nem)
A80: timeseries.inflation | B80: 1 | C80: Idősor infláció-szűrő megjelenítése? (1 = Igen, 0 = Nem)
A81: timeseries.gdp | B81: 0 | C81: Idősor GDP megjelenítése? (1 = Igen, 0 = Nem)
A82: timeseries.expense | B82: Kiadások idősorban | C82: Idősor kiadások szakasz címsora.
A83: timeseries.expenseText | B83: Ez itt a kiadások idősora. Ide szöveget a config excelben a timeseries.expenseText kulcsnál lehet megadni. | C83: Idősor kiadások szakasz magyarázata.
A84: timeseries.income | B84: Bevételek idősorban | C84: Idősor bevételek szakasz címsora.
A85: timeseries.incomeText | B85: Ez itt a kiadások idősora. Ide szöveget a config excelben a timeseries.incomeText kulcsnál lehet megadni. | C85: Idősor bevételek szakasz magyarázata.
A87: inflations.2010 | B87: 4.9 | C87: Idősor infláció adatok az infláció-szűrő funkcióhoz. A pont után az év elnevezése szerepel.
A88: inflations.2011 | B88: 3.9 | C88: Idősor infláció adatok az infláció-szűrő funkcióhoz. A pont után az év elnevezése szerepel.
A89: inflations.2012 | B89: 5.7 | C89: Idősor infláció adatok az infláció-szűrő funkcióhoz. A pont után az év elnevezése szerepel.
A90: inflations.2013 | B90: 1.7 | C90: Idősor infláció adatok az infláció-szűrő funkcióhoz. A pont után az év elnevezése szerepel.
A91: inflations.2014 | B91: -0.2 | C91: Idősor infláció adatok az infláció-szűrő funkcióhoz. A pont után az év elnevezése szerepel.
A92: inflations.2015 | B92: -0.1 | C92: Idősor infláció adatok az infláció-szűrő funkcióhoz. A pont után az év elnevezése szerepel.
A93: inflations.2016 | B93: 0.4 | C93: Idősor infláció adatok az infláció-szűrő funkcióhoz. A pont után az év elnevezése szerepel.
A94: inflations.2017 | B94: 2.4 | C94: Idősor infláció adatok az infláció-szűrő funkcióhoz. A pont után az év elnevezése szerepel.
A95: inflations.2018 | B95: 2.8 | C95: Idősor infláció adatok az infláció-szűrő funkcióhoz. A pont után az év elnevezése szerepel.
A96: inflations.2019 | B96: 3.4 | C96: Idősor infláció adatok az infláció-szűrő funkcióhoz. A pont után az év elnevezése szerepel.
A97: inflations.2020 | B97: 3.3 | C97: Idősor infláció adatok az infláció-szűrő funkcióhoz. A pont után az év elnevezése szerepel.
A98: inflations.2021 | B98: 5.1 | C98: Idősor infláció adatok az infláció-szűrő funkcióhoz. A pont után az év elnevezése szerepel.
... A112: gdps.2024 | B112: 81447664000000 | C112: Idősor GDP adatok a GDP arányos megjelenítéshez. A pont után az év elnevezése szerepel.
A113: gdps.2025 | C113: Idősor GDP adatok a GDP arányos megjelenítéshez. A pont után az év elnevezése szerepel.
A115: feedback.title | B115: Visszajelzés | C115: Visszajelzés ablak címsora.
A116: feedback.text | B116: Kérjük, véleményezze a költségvetést bemutató oldalunkat, hogy még jobbá tehessük azt! | C116: Visszajelzésre buzdító szöveg.
A117: feedback.action | B117: Kérdőív kitöltése | C117: Visszajelző űrlapra mutató link szövege.
A118: feedback.url | B118: https://forms.gle/SKMdYvfrFEZTXq6V8 | C118: Visszajelző űrlap URL-je.
A120: footer.url | B120: https://www.terezvaros.hu/ | C120: Kontakt weboldal címe.
A121: footer.fb | B121: terezvaros.hu | C121: Kontakt Facebook oldal azonosítója.
A122: footer.email | B122: sajto@terezvaros.hu | C122: Kontakt email cím.
A124: iframe.title | B124: Közérdekű adatok | C124: Iframe-es oldal elnevezése. A fenti menüsorban jelenik meg.
A125: iframe.url | B125: https://terezvaros.hu/atlathatosag | C125: Iframe-es oldalban beágyazott URL.
A127: ga.id | C127: Google Analytics azonosító (UA-XXXXXXXXX-X)
A128: gtm.id | B128: GTM-PQ5C44CX | C128: Google Tag Manager azonosító (GTM-XXXXXXX)
A130: font.imports | C130: Webfonto(ka)t importáló CSS kód, pl: `@import url('https://...');`, lehet több ilyen a cellában.
A131: font.base | C131: Alap betűtípus neve, alapértelmezetthez (Roboto Condensed) hagyd üresen.
A132: font.headings | B132: Titillium Web | C132: Fejlécek betűtípusának neve, font.base használatához hagyd üresen.
A133: font.vis | C133: Ábrák betűtípusának neve, font.base használatához hagyd üresen.
A135: theme.2020 | B135: #558C8C | C135: A pont után szereplő év főszíne.
A136: theme.2021 | B136: #558C8C | C136: A pont után szereplő év főszíne.
A137: theme.2022 | B137: #558C8C | C137: A pont után szereplő év főszíne.
A138: theme.2023 | B138: #558C8C | C138: A pont után szereplő év főszíne.
A139: theme.2024 | B139: #558C8C | C139: A pont után szereplő év főszíne.
A140: theme.2025 | B140: #558C8C | C140: A pont után szereplő év főszíne.
A141: theme.2026 | B141: #f04e3e | C141: A pont után szereplő év főszíne.
A143: inex.B1 | B143: #61C1D6
A144: inex.B2 | B144: #61C1D6
A145: inex.B3 | B145: #61C1D6
A146: inex.B4 | B146: #B56DB6
A147: inex.FT1 | B147: #FFD074
A148: inex.B5 | B148: #FFD074
A149: inex.B6 | B149: #FFD074
...

Sheet tooltips 2020
A1: Azon. | B1: Megnevezés | C1: Súgószöveg
A2: B1 | B2: Működési célú támogatások államháztartáson belülről | C2: Döntően a központi költségvetésből kapott, normatív alapon járó feladatfinanszírozási és kiegészítő támogatások.
A3: B11 | B3: Önkormányzatok működési támogatásai | C3: Döntően a központi költségvetésből a napi működés kötelező feladataira kapott, kötött felhasználású támogatások tartoznak ide.
A4: B1101 | B4: Önkormányzatok működésének általános támogatása | C4: A központi költségvetésből az önkormányzatok részére, pl. a hivatal működtetésére, településüzemeltetésre (zöldterület-gazdálkodás, közvilágítás, köztemetők) juttatott feladatalapú támogatás.
A5: B1102 | B5: Önkormányzatok egyes köznevelési feladatainak támogatása | C5: A központi költségvetésből az önkormányzatok egyes köznevelési feladatainak (pl. óvodaműködtetés) támogatására biztosított feladatalapú és kiegészítő támogatások.
A6: B1103 | B6: Önkormányzatok szociális gyermekjóléti és gyermekétkeztetési feladatainak támogatása | C6: A központi költségvetésből az önkormányzatok szociális, gyermekjóléti és gyermekétkeztetési feladatainak (ide értve a bölcsődéket) támogatására biztosított feladatalapú és kiegészítő támogatások.
A7: B1104 | B7: Önkormányzatok kulturális feladatainak támogatása | C7: A központi költségvetésből az önkormányzatok könyvtári, közművelődési és múzeumi feladatainak támogatására biztosított feladatalapú és kiegészítő támogatások.
A8: B12 | B8: Egyéb működési célú támogatások bevételei államháztartáson belülről | C8: A Nemzeti Egészségbiztosítási Alapkezelőtől egészségügyi és szociális feladatok ellátására érkező összeg. Ez az összeg a Terézvárosi Egészségügyi Szolgálat és a Terézvárosi Gondozó Szolgálat bevételeinek egy részét képezi.
A9: B2 | B9: Közhatalmi bevételek | C9: A lakosok és a helyi vállalatok által befizetett helyi adók, díjak, bírságok.
A10: B21 | B10: Vagyoni típusú adók | C10: Építményadóból, telekadóból származó bevételek.
A11: B2101 | B11: Építményadó | C11: Az építményadót a Terézvárosban lévő nem lakás céljára szolgáló épületek, épületrészek után kell fizetni. Rendeltetéstől, hasznosítástól függetlenül valamennyi helyiségre kiterjed az adókötelezettség. Az adó alapját a m2-ben számított hasznos alapterület adja.
A12: B2102 | B12: Telekadó | C12: A telekadót a Terézvárosban lévő telek, azaz épülettel, épületrésszel be nem épített földterület után kell fizetni. A telekadó alapját a telek m2-ben számított területe adja.
... A15: B24 | B15: Idegenforgalmi adó | C15: Helyi adó, amelyet a kerületben eltöltött vendégéjszakák után személyenként kell megfizetni.
A16: B25 | B16: Egyéb közhatalmi bevételek (díjak, bírságok, pótlékok )
A17: B3 | B17: Működési bevételek és átvett pénzeszközök | C17: Olyan működéshez köthető bevételek, amelyek nem tartoznak a támogatások, az adóbevételek közé, és nem értékesítésből származnak (például parkolási bevételek, az üzlethelységek, lakások bérleti díja, járóbeteg-ellátáshoz kapott központi támogatás).
A18: B31 | B18: Nyújtott szolgáltatás ellenértéke | C18: Nyújtott szolgáltatásokért elsősorban a költségvetési szervek tesznek szert bevételre. Így jut bevételhez például a Terézvárosi Egészségügyi Szolgálat a díjköteles egészségügyi szolgáltatásokért.
A19: B32 | B19: Közvetített szolgáltatások ellenértéke | C19: A közvetített szolgáltatásokért jellemzően a Belső-Pesti Tankerületi Központ fizet az önkormányzatnak.
A20: B33 | B20: Tulajdonosi bevételek | C20: Parkolásüzemeltetésből, lakások és helyiségek bérleti díjából, közterülethasználati díjból származó önkormányzati bevételek .
A21: B3301 | B21: Parkolási bevétel a fővárosi területeken | C21: A fővárosi tulajdonú közterületeken is a kerületek üzemeltetik a parkolóhelyeket, de a parkolásból származó bevételek – a kerületi költségek levonása után – a fővárosi önkormányzatot illetik. A kerületnek a feladat ellátásából származó bevétele és kiadása ugyanakkora összeget tesz ki. Ez az összeg a kiadások között is megjelenik.
A22: B3302 | B22: Helyiségbérleti-díj bevétel | C22: Az önkormányzat tulajdonában álló, nem lakáscélú helységek bérbeadásából származó bérleti díjak.
A23: B3303 | B23: Lakásbérleti-díj bevétel | C23: Az önkormányzat tulajdonában álló lakások bérbeadásából származó bérleti díjak.
A24: B3304 | B24: Közterülethasználati díjból származó bevétel
A25: B3305 | B25: Haszonbérlet és egyéb parkolási bevétel | C25: A parkolási bevételek a vagyonkezelő céget illetik, de az önkormányzattal kötött haszonbérleti szerződésnek megfelelően a Vagyonkezelő a bevételből havi 50 millió forint + áfát fizet az önkormányzatnak.
A26: B3306 | B26: Piacüzemeltetésből származó bevétel
A27: B3307 | B27: Egyéb tulajdonnal összefüggő bevétel (víz, csatorna, szemét)
A28: B34 | B28: Ellátási díjak | C28: Bölcsődékben, óvodákban, iskolákban az étkezésért fizetett díjakból származó bevételek. Az étkezésért az azt igénybe vevők kb. 60%-a fizet, a többiek ingyenesen vagy kedvezményesen étkeznek.
A29: B35 | B29: Kiszámlázott általános forgalmi adó | C29: A tulajdonosi bevételek (például helyiség-bérbeadásból származó bevételek) áfája.
A30: B36 | B30: Általános forgalmi adó visszatérítése | C30: Az önkormányzati áfás kiadások után visszaigényelhető összeg (például étkeztetés, közüzemi díjak áfája esetében).
A31: B37 | B31: Kamatbevételek | C31: Az államkötvényben tartott befektetésekből származó kamatbevételek.
A32: B38 | B32: Működési célú átvett átvett pénzeszközök | C32: Járóbeteg-ellátáshoz kapott központi támogatás
A33: B4 | B33: Felhalmozási bevételek, támogatások, átvett pénzeszközök | C33: Ingatlanértékesítésből, fővárosi támogatásból, társasházi kölcsönök visszafizetéséből származó bevételek.
A34: B41 | B34: Felhalmozási célú támogatás államháztartáson belülről | C34: A Fővárostól pályázaton elnyert támogatás összege.
A35: B42 | B35: Felhalmozási bevételek - ingatlanértékesítés | C35: A tervezett ingatlanértékesítésből származó bevételek.
A36: B43 | B36: Felhalmozási célú átvett pénzeszközök | C36: A társasházi kölcsönökből származó visszafizetések.
A37: B5 | B37: Finanszírozási bevételek - maradvány igénybevétele | C37: Az előző évi maradvány összege.
A38: FT1 | B38: Finanszírozási bevétel - maradvány | C38: Az előző évi maradvány összege.
A39: K1 | B39: Személyi juttatások és járulékok | C39: Személyi kiadások és a munkáltató által fizetett járulékaik
... A41: K1101 | B41: Külső személyi juttatások | C41: Feladatot ellátó, nem foglalkoztatotti viszonyban lévő személyek juttatásai
A42: K1102 | B42: Munkaadókat terhelő járulékok és szociális hozzájárulási adó
A43: K12 | B43: Polgármesteri hivatal személyi juttatásai és járulékai | C43: Személyi kiadások és a munkáltató által fizetett járulékaik
A44: K1201 | B44: Foglalkoztatottak személyi juttatásai
A45: K1202 | B45: Külső személyi juttatások | C45: Feladatot ellátó, nem foglalkoztatotti viszonyban lévő személyek juttatásai
A46: K1203 | B46: Munkaadókat terhelő járulékok és szociális hozzájárulási adó
A47: K13 | B47: Óvodák személyi juttatásai és járulékai | C47: Személyi kiadások és a munkáltató által fizetett járulékaik
A48: K1301 | B48: Fasori óvoda személyi juttatásai és járulékai | C48: Személyi kiadások és a munkáltató által fizetett járulékaik
A49: K130101 | B49: Foglalkoztatottak személyi juttatásai
A50: K130102 | B50: Külső személyi juttatások | C50: Feladatot ellátó, nem foglalkoztatotti viszonyban lévő személyek juttatásai
A51: K130103 | B51: Munkaadókat terhelő járulékok és szociális hozzájárulási adó
A52: K1302 | B52: Játékvár óvoda személyi juttatásai és járulékai | C52: Személyi kiadások és a munkáltató által fizetett járulékaik
A53: K130201 | B53: Foglalkoztatottak személyi juttatásai
A54: K130202 | B54: Külső személyi juttatások | C54: Feladatot ellátó, nem foglalkoztatotti viszonyban lévő személyek juttatásai
A55: K130203 | B55: Munkaadókat terhelő járulékok és szociális hozzájárulási adó
A56: K1303 | B56: Szív óvoda személyi juttatásai és járulékai | C56: Személyi kiadások és a munkáltató által fizetett járulékaik
A57: K130301 | B57: Foglalkoztatottak személyi juttatásai
A58: K130302 | B58: Külső személyi juttatások | C58: Feladatot ellátó, nem foglalkoztatotti viszonyban lévő személyek juttatásai
A59: K130303 | B59: Munkaadókat terhelő járulékok és szociális hozzájárulási adó
A60: K1304 | B60: Mesevilág óvoda személyi juttatásai és járulékai | C60: Személyi kiadások és a munkáltató által fizetett járulékaik
A61: K130401 | B61: Foglalkoztatottak személyi juttatásai
A62: K130402 | B62: Külső személyi juttatások | C62: Feladatot ellátó, nem foglalkoztatotti viszonyban lévő személyek juttatásai
A63: K130403 | B63: Munkaadókat terhelő járulékok és szociális hozzájárulási adó
A64: K1305 | B64: Kincseskert óvoda személyi juttatásai és járulékai | C64: Személyi kiadások és a munkáltató által fizetett járulékaik
A65: K130501 | B65: Foglalkoztatottak személyi juttatásai
A66: K130502 | B66: Külső személyi juttatások | C66: Feladatot ellátó, nem foglalkoztatotti viszonyban lévő személyek juttatásai
A67: K130503 | B67: Munkaadókat terhelő járulékok és szociális hozzájárulási adó
A68: K14 | B68: Terézvárosi Egészségügyi Szolgálat személyi juttatásai és járulékai | C68: Személyi kiadások és a munkáltató által fizetett járulékaik
A69: K1401 | B69: Foglalkoztatottak személyi juttatásai
A70: K1402 | B70: Külső személyi juttatások | C70: Feladatot ellátó, nem foglalkoztatotti viszonyban lévő személyek juttatásai
A71: K1403 | B71: Munkaadókat terhelő járulékok és szociális hozzájárulási adó
A72: K15 | B72: Terézvárosi Értelmi Fogyatékosok Napközi Otthona személyi juttatásai és járulékai | C72: Személyi kiadások és a munkáltató által fizetett járulékaik
A73: K1501 | B73: Foglalkoztatottak személyi juttatásai
A74: K1502 | B74: Külső személyi juttatások | C74: Feladatot ellátó, nem foglalkoztatotti viszonyban lévő személyek juttatásai
A75: K1503 | B75: Munkaadókat terhelő járulékok és szociális hozzájárulási adó
A76: K16 | B76: Terézvárosi Gondozó Szolgálat személyi juttatásai és járulékai | C76: Személyi kiadások és a munkáltató által fizetett járulékaik
A77: K1601 | B77: Foglalkoztatottak személyi juttatásai
A78: K1602 | B78: Külső személyi juttatások | C78: Feladatot ellátó, nem foglalkoztatotti viszonyban lévő személyek juttatásai
A79: K1603 | B79: Munkaadókat terhelő járulékok és szociális hozzájárulási adó
A80: K17 | B80: Terézvárosi Család- és Gyermekjóléti Központ személyi juttatásai és járulékai | C80: Személyi kiadások és a munkáltató által fizetett járulékaik
A81: K1701 | B81: Foglalkoztatottak személyi juttatásai
A82: K1702 | B82: Külső személyi juttatások | C82: Feladatot ellátó, nem foglalkoztatotti viszonyban lévő személyek juttatásai
A83: K1703 | B83: Munkaadókat terhelő járulékok és szociális hozzájárulási adó
A84: K18 | B84: Terézvárosi Egyesített Bölcsődék személyi juttatásai és járulékai | C84: Személyi kiadások és a munkáltató által fizetett járulékaik
A85: K1801 | B85: Foglalkoztatottak személyi juttatásai
A86: K1802 | B86: Külső személyi juttatások | C86: Feladatot ellátó, nem foglalkoztatotti viszonyban lévő személyek juttatásai
A87: K1803 | B87: Munkaadókat terhelő járulékok és szociális hozzájárulási adó
A88: K2 | B88: Dologi kiadások | C88: A mindennapi működéshez, a feladatok ellátásához szükséges kiadások.
A89: K21 | B89: Önkormányzat dologi kiadásai | C89: A mindennapi működéshez, a feladatok ellátásához szükséges kiadások.
A90: K2101 | B90: Készletbeszerzés | C90: Működtetéshez szükséges eszközök, például nyomtatványok, irodaszerek beszerzésére fordított összeg.
A91: K2102 | B91: Kommunikációs szolgáltatások | C91: Távközlési díjak (internet, telefon), honlapfejlesztés, videókészítés.
A92: K2103 | B92: Szolgáltatási kiadások | C92: A dologi kiadások tetemes részét szolgáltatások vásárlására költi az önkormányzat. Ilyenek például: lakóépületek karbantartása, közös költség fizetés, étkeztetés, bérleti jogviszony megváltása.
A93: K2104 | B93: Kiküldetés
A94: K2105 | B94: Különféle befizetések és dologi kiadások | C94: Legnagyobb tétele az önkormányzat által kifizetett áfa.
A95: K22 | B95: Polgármesteri hivatal | C95: A mindennapi működéshez, a feladatok ellátásához szükséges kiadások.
A96: K23 | B96: Óvodák dologi kiadásai | C96: A mindennapi működéshez, a feladatok ellátásához szükséges kiadások.
A97: K2301 | B97: Fasori óvoda dologi kiadásai | C97: A mindennapi működéshez, a feladatok ellátásához szükséges kiadások.
A98: K2302 | B98: Játékvár óvoda dologi kiadásai | C98: A mindennapi működéshez, a feladatok ellátásához szükséges kiadások.
A99: K2303 | B99: Szív óvoda dologi kiadásai | C99: A mindennapi működéshez, a feladatok ellátásához szükséges kiadások.
A100: K2304 | B100: Mesevilág óvoda dologi kiadásai | C100: A mindennapi működéshez, a feladatok ellátásához szükséges kiadások.
A101: K2305 | B101: Kincseskert óvoda dologi kiadásai | C101: A mindennapi működéshez, a feladatok ellátásához szükséges kiadások.
A102: K24 | B102: Terézvárosi Egészségügyi Szolgálat dologi kiadásai | C102: A mindennapi működéshez, a feladatok ellátásához szükséges kiadások.
A103: K25 | B103: Terézvárosi Értelmi Fogyatékosok Napközi Otthona dologi kiadásai | C103: A mindennapi működéshez, a feladatok ellátásához szükséges kiadások.
...

Sheet tooltips 2021
A1: Azon. | B1: Megnevezés | C1: Súgószöveg
A2: 1 | B2: Általános közszolgáltatások | C2: Az általános közszolgáltatások több, mint fele az önkormányzat vagyonának megőrzéséhez és fejlesztéséhez kapcsolódó kiadások. Jókai tér, Vásárcsarnok felújítása, Aradi utca 22. szám alatti bérház felújítása, iskolák felújítása, Csengery utca teljes körű megújítása. Az általános közszolgáltatások másik része a hivatal és az önkormányzati intézmények működtetése.
A3: 10 | B3: Szociális védelem | C3: A bölcsődei, család- és gyermekjóléti szolgáltatások, segélyek, ellátások, támogatások
A4: 1012 | B4: Fogyatékosság | C4: TERÉZÉNO fenntartása
A5: 101221 | B5: Fogyatékossággal élők nappali ellátása | C5: TERÉZÉNO fenntartása
A6: 1020 | B6: Időskor, demens betegek | C6: TEGOSZ nyugdíjas klubjának fenntartása
A7: 102031 | B7: Idősek nappali ellátása | C7: TEGOSZ nyugdíjas klubjának fenntartása
A8: 1040 | B8: Család és gyermekek | C8: A bölcsődék és a családsegítő központ fenntartása, különböző gyermekvédelmi, család- és gyermekjóléti, családtámogatási ellátások, juttatások
A9: 104012 | B9: Gyermekek átmeneti ellátása
A10: 104031 | B10: Gyermekek bölcsődei ellátása
A11: 104035 | B11: Gyermekétkeztetés bölcsődében, fogyatékossággal élők nappali intézményében
A12: 104036 | B12: Munkahelyi étkeztetés bölcsődében
A13: 104037 | B13: Intézményen kívüli gyermekétkeztetés
A14: 104042 | B14: Család- és gyermekjóléti szolgáltatások
A15: 104043 | B15: Család- és gyermekjóléti központ
A16: 104051 | B16: Gyermekvédelmi pénzbeli és természetbeni ellátások
A17: 1070 | B17: Egyéb szociális kirekesztettség | C17: Terézvárosi Gondozó Szolgálat (TEGOSZ) fenntartása, szociális étkeztetés, házi segítségnyújtás, jelzőrendszeres házi segítségnyújtás
A18: 107051 | B18: Szociális étkeztetés
A19: 107052 | B19: Házi segítségnyújtás
A20: 107053 | B20: Jelzőrendszeres házi segítségnyújtás
A21: 107060 | B21: Egyéb szociális pénzbeli és természetbeni ellátások, támogatások
A22: 111 | B22: Államhatalmi, törvényhozó és végrehajtó szervezetek | C22: Az önkormányzat és az önkormányzati hivatal jogalkotó és általános igazgatási tevékenysége, ideértve a nemzetiségi önkormányzatok igazgatását is
A23: 11130 | B23: Önkormányzatok és önkormányzati hivatalok jogalkotó és általános igazgatási tevékenysége | C23: A polgármesteri hivatal kiadásai, a képviselők és választott tisztségviselők juttatásai, a polgármesteri tisztséggel összefüggő egyéb kiadások
A24: 112 | B24: Pénzügyi és költségvetési tevékenységek, adózási ügyek
A25: 11220 | B25: Adó-, vám- és jövedéki igazgatás
A26: 133 | B26: Egyéb általános szolgáltatások | C26: Állampolgársági ügyek, kiemelt rendezvények
A27: 13350 | B27: Az önkormányzati vagyonnal való gazdálkodással kapcsolatos feladatok
A28: 180 | B28: Általános jellegű transzferek a kormányzat különböző szintjei között
A29: 18020 | B29: Központi költségvetési befizetések | C29: A szolidaritási hozzájárulási adó befizetése
A30: 3 | B30: Közrend és közbiztonság | C30: Városrendészet működtetésének költségei, térfigyelőkamera-rendszer fejlesztése és üzemeltetése
A31: 310 | B31: Rendészeti tevékenységek | C31: Városrendészet működtetésének költségei, térfigyelő kamerarendszer fejlesztése és üzemeltetése
A32: 31030 | B32: Közterület rendjének fenntartása | C32: Városrendészet működtetésének költségei, térfigyelő kamerarendszer fejlesztése és üzemeltetése
A33: 4 | B33: Gazdasági ügyek | C33: Közterületek takarításának költségei, közutak, járdák felújítása és fenntartása, vásárcsarnok és piac üzemeltetése, hatósági állatorvosi feladatok ellátása
A34: 411 | B34: Általános gazdasági és kereskedelmi ügyek | C34: Zajmérési vizsgálatok
A35: 41170 | B35: Műszaki vizsgálat, elemzés | C35: Zajmérési vizsgálatok
A36: 412 | B36: Általános munkaügyek | C36: Közterületek takarításának költségei
A37: 41233 | B37: Hosszabb időtartamú közfoglalkoztatás | C37: Közterületek takarításának költségei
A38: 421 | B38: Mezőgazdaság | C38: Hatósági állatorvosi feladatok ellátása
A39: 42180 | B39: Állategészségügy | C39: Hatósági állatorvosi feladatok ellátása
A40: 451 | B40: Közúti közlekedés | C40: Közutak, járdák felújítása és fenntartása
... A50: 7 | B50: Egészségügy | C50: Az egészségügyi kiadások nagy része a Terézvárosi Egészségügyi Szolgálat (TESZ) működtetése: járóbeteg-ellátás, szakorvosi ellátás, védőnői szolgálat, fogorvosi ellátás.
A51: 721 | B51: Általános orvosi szolgáltatások
A52: 72111 | B52: Háziorvosi alapellátás
A53: 72112 | B53: Háziorvosi ügyeleti ellátás
A54: 722 | B54: Szakosított orvosi szolgáltatások
A55: 72210 | B55: Járóbetegek gyógyító szakellátása
A56: 72220 | B56: Járóbetegek rehabilitációs szakellátása
A57: 72230 | B57: Járóbetegek gyógyító gondozása
A58: 723 | B58: Fogorvosi szolgáltatások
A59: 72311 | B59: Fogorvosi alapellátás
A60: 72313 | B60: Fogorvosi szakellátás
A61: 724 | B61: Paramedikális szolgáltatások
A62: 72410 | B62: Otthoni (egészségügyi) szakápolás
... A70: 74040 | B70: Fertőző megbetegedések megelőzése, járványügyi ellátás
A71: 8 | B71: Szabadidő | C71: Eötvös10 Kulturális Színtér működtetése, Terézváros magazin fenntartása és egyéb lakossági tájékoztatási feladatok ellátása, civil és egyházi szervezetek támogatása, önkormányzat fenntartásában működő siófoki üdülő és dunabogdányi nyári tábor és erdei iskola működtetése
A72: 810 | B72: Szabadidős és sportszolgáltatások | C72: Önkormányzat fenntartásában működő siófoki üdülő és dunabogdányi nyári tábor és erdei iskola működtetése
A73: 81071 | B73: Üdülői szálláshely-szolgáltatás és étkeztetés | C73: Önkormányzat fenntartásában működő üdülők és dunabogdányi nyári tábor és erdei iskola működtetése
A74: 820 | B74: Kulturális szolgáltatások | C74: Eötvös10 Kulturális Színtér működtetése
A75: 82092 | B75: Közművelődés - hagyományos közösségi kulturális értékek gondozása | C75: Eötvös10 Kulturális Színtér működtetése
A76: 830 | B76: Műsorszolgáltatási és kiadói szolgáltatások | C76: Terézváros magazin fenntartása és egyéb lakossági tájékoztatási feladatok ellátása
A77: 83030 | B77: Egyéb kiadói tevékenység | C77: Terézváros magazin fenntartása és egyéb lakossági tájékoztatási feladatok ellátása
A78: 83050 | B78: Televízió-műsor szolgáltatása és támogatása | C78: Egyéb lakossági tájékoztatási feladatok ellátása
A79: 840 | B79: Vallási és egyéb közösségi szolgáltatások | C79: Civil és egyházi szervezetek támogatása
A80: 84031 | B80: Civil szervezetek működési támogatása | C80: Civil és egyházi szervezetek támogatása
A81: 9 | B81: Oktatás | C81: Óvodák fenntartása, óvodai nevelés, gyermekétkeztetés kiadásai
A82: 911 | B82: Óvodai nevelés
A83: 91110 | B83: Óvodai nevelés, ellátás szakmai feladatai
A84: 91120 | B84: Sajátos nevelési igényű gyermekek óvodai nevelésének, ellátásának szakmai feladatai
A85: 91130 | B85: Nemzetiségi óvodai nevelés, ellátás szakmai feladatai
A86: 91140 | B86: Óvodai nevelés, ellátás működtetési feladatai
A87: 960 | B87: Oktatást kiegészítő szolgáltatások | C87: Gyermekétkeztetés kiadásai
A88: 96015 | B88: Gyermekétkeztetés köznevelési intézményben
A89: B1 | B89: Működési célú támogatások államháztartáson belülről | C89: Döntően a központi költségvetésből kapott, normatív alapon járó, feladatfinanszírozási és kiegészítő támogatások
A90: B11 | B90: Önkormányzatok működési támogatásai | C90: Döntően a központi költségvetésből a napi működés kötelező feladataira kapott, kötött felhasználású támogatások
A91: B1101 | B91: Önkormányzatok működésének általános támogatása | C91: A központi költségvetésből az önkormányzatok részére, pl. a hivatal működtetésére, településüzemeltetésre (zöldterület-gazdálkodás, közvilágítás, köztemetők) juttatott feladatalapú támogatás
A92: B110101 | B92: Polgármesteri hivatal működésének támogatása | C92: A központi költségvetésből a hivatal működésének támogatása
A93: B110102 | B93: Településüzemeltetés - zöldterület-gazdálkodás támogatása | C93: A központi költségvetésből a településüzemeltetés támogatása
A94: B110103 | B94: Településüzemeltetés - közutak támogatása | C94: A központi költségvetésből a településüzemeltetés támogatása
A95: B110104 | B95: Egyéb önkormányzati feladatok támogatása | C95: A központi költségvetésből az egyéb önkormányzati feladatok támogatása
A96: B1102 | B96: Önkormányzatok egyes köznevelési feladatainak támogatása | C96: A központi költségvetésből az önkormányzatok egyes köznevelési feladatainak, pl. óvodaműködtetés támogatására biztosított feladatalapú és kiegészítő támogatások
A97: B110201 | B97: Óvodaműködtetési támogatás | C97: Központi költségvetésből az óvodák működtetésének támogatása
A98: B110202 | B98: Az óvodákban foglalkoztatott pedagógusok átlagbéralapú támogatása | C98: Központi költségvetésből az óvodák működtetésének támogatása
A99: B110203 | B99: Kiegészítő támogatás a pedagógusok és a pedagógus szakképzettséggel rendelkező segítők minősítéséből adódó többletkiadásokhoz | C99: Központi költségvetésből az óvodák működtetésének támogatása
A100: B110204 | B100: Nemzetiségi pótlék | C100: Központi költségvetésből az óvodák működtetésének támogatása
... A124: B3304 | B124: Haszonbérlet és egyéb parkolási bevétel | C124: A parkolási bevételek a vagyonkezelő céget illetik, de az önkormányzattal kötött haszonbérleti szerződésnek megfelelően a Vagyonkezelő a bevételből havi 50 millió forint + áfát fizet az önkormányzatnak
A125: B3305 | B125: Piacüzemeltetésből származó bevétel
A126: B3306 | B126: Egyéb tulajdonnal összefüggő bevétel (víz, csatorna, szemét)
A127: B34 | B127: Ellátási díjak | C127: Bölcsődékben, óvodákban, iskolákban az étkezésért fizetett díjakból származó bevételek. Az étkezésért az azt igénybe vevők kb. 60%-a fizet, a többiek ingyenesen vagy kedvezményesen étkeznek.
A128: B35 | B128: Kiszámlázott általános forgalmi adó | C128: A tulajdonosi bevételek (például helyiség-bérbeadásból származó bevételek) áfája
A129: B36 | B129: Általános forgalmi adó visszatérítése | C129: Az önkormányzati áfás kiadások után visszaigényelhető összeg (például étkeztetés, közüzemi díjak áfája esetében)
A130: B37 | B130: Kamatbevételek | C130: Az államkötvényben tartott befektetésekből származó kamatbevételek
A131: B38 | B131: Egyéb működési bevételek | C131: Késedelmi kamatokból származó bevétel (ingatlanbérleti díjak után)
A132: B39 | B132: Működési célú átvett pénzeszközök | C132: Járóbeteg-ellátáshoz kapott központi támogatás
A133: B4 | B133: Felhalmozási bevételek, támogatások, átvett pénzeszközök | C133: Ingatlanértékesítésből származó bevételek, Fővárostól kapott támogatás, társasházi kölcsönök visszafizetései
A134: B41 | B134: Ingatlanok értékesítése | C134: A tervezett ingatlanértékesítésből származó bevételek
A135: B42 | B135: Felhalmozási célú támogatás államháztartáson belülről | C135: A Fővárostól a Jókai tér felújításához kapott támogatás összege
A136: B43 | B136: Felhalmozási célú átvett pénzeszközök | C136: A társasházi kölcsönökből származó visszafizetések
A137: B5 | B137: Finanszírozási bevételek | C137: Az előző évi maradványok, értékpapírok beváltásából származó bevételek
A138: B51 | B138: Belföldi értékpapírok bevételei | C138: Értékpapírok beváltásából származó bevétel.
... A143: K1101 | B143: Külső személyi juttatások | C143: Feladatot ellátó, nem foglalkoztatotti viszonyban lévő személyek juttatásai
...

Sheet tooltips 2022
A1: Azon. | B1: Megnevezés | C1: Súgószöveg
A2: 1 | B2: Általános közszolgáltatások | C2: Az általános közszolgáltatások több, mint fele az önkormányzat vagyonának megőrzéséhez és fejlesztéséhez kapcsolódó kiadások, illetve a hivatal és az önkormányzati intézmények működtetése, döntéshozatala, igazgatása.
A3: 10 | B3: Szociális védelem | C3: A bölcsődei, család- és gyermekjóléti szolgáltatások, segélyek, ellátások, támogatások.
A4: 1012 | B4: Fogyatékosság | C4: TERÉZÉNO fenntartása
A5: 101221 | B5: Fogyatékossággal élők nappali ellátása | C5: TERÉZÉNO fenntartása
A6: 1020 | B6: Időskor, demens betegek | C6: TEGOSZ nyugdíjas klubjának fenntartása
A7: 102031 | B7: Idősek nappali ellátása | C7: TEGOSZ nyugdíjas klubjának fenntartása
A8: 1040 | B8: Család és gyermekek | C8: A bölcsődék és a családsegítő központ fenntartása, különböző gyermekvédelmi, család- és gyermekjóléti, családtámogatási ellátások, juttatások.
A9: 104012 | B9: Gyermekek átmeneti ellátása | C9: Terézvárosi Család- és Gyermekjóléti Központ tevékenysége.
A10: 104030 | B10: Gyermekek napközbeni ellátása
A11: 104031 | B11: Gyermekek bölcsődei ellátása
A12: 104035 | B12: Gyermekétkeztetés bölcsődében, fogyatékosok nappali intézményében
A13: 104036 | B13: Munkahelyi étkeztetés bölcsődében
A14: 104037 | B14: Intézményen kívüli gyermekétkeztetés
A15: 104042 | B15: Család és gyermekjóléti szolgáltatások
A16: 104043 | B16: Család és gyermekjóléti központ
A17: 1070 | B17: Egyéb szociális kirekesztettség | C17: Terézvárosi Gondozó Szolgálat (TEGOSZ) fenntartása, szociális étkeztetés, házi segítségnyújtás, jelzőrendszeres házi segítségnyújtás
A18: 107051 | B18: Szociális étkeztetés
A19: 107052 | B19: Házi segítségnyújtás
A20: 107053 | B20: Jelzőrendszeres házi segítségnyújtás
A21: 107054 | B21: Családsegítés
A22: 107060 | B22: Egyéb szociális pénzbeli és természetbeni ellátások, támogatások
A23: 111 | B23: Államhatalmi, törvényhozó és végrehajtó szervezetek | C23: Az önkormányzat és az önkormányzati hivatal jogalkotó és általános igazgatási tevékenysége, ideértve a nemzetiségi önkormányzatok igazgatását is.
A24: 11130 | B24: Önkormányzatok és önkormányzati hivatalok jogalkotó és általános igazgatási tevékenysége | C24: A polgármesteri hivatal kiadásai, a képviselők és választott tisztségviselők juttatásai, a polgármesteri tisztséggel összefüggő egyéb kiadások.
A25: 112 | B25: Pénzügyi és költségvetési tevékenységek, adózási ügyek
A26: 11220 | B26: Adó-, vám- és jövedéki igazgatás | C26: A Hivatal adóügyi osztályának működése.
A27: 133 | B27: Egyéb általános szolgáltatások | C27: Vagyongazdálkodási kiadások, amelyek döntően a Vagyonkezelőhöz kötődnek.
A28: 13350 | B28: Az önkormányzati vagyonnal való gazdálkodással kapcsolatos feladatok | C28: Döntően a Vagyonkezelő Zrt. különböző tevékenységeinek kiadásai (karbantartás, javítás, projektmenedzsment, önkormányzati tulajdon után fizetett közös költség stb.)
A29: 180 | B29: Általános jellegű transzferek a kormányzat különböző szintjei között | C29: A központi költségvetésbe fizetendő szolidaritási adó jelenik meg itt.
A30: 18020 | B30: Központi költségvetési befizetések | C30: A központi költségvetésbe fizetendő szolidaritási adó jelenik meg itt.
A31: 3 | B31: Közrend és közbiztonság | C31: Városrendészet működtetésének költségei, térfigyelőkamera-rendszer fejlesztése és üzemeltetése
A32: 310 | B32: Rendészeti tevékenységek | C32: Városrendészet működtetésének költségei, térfigyelő kamerarendszer fejlesztése és üzemeltetése
A33: 31030 | B33: Közterület rendjének fenntartása | C33: Városrendészet működtetésének költségei, térfigyelő kamerarendszer fejlesztése és üzemeltetése
A34: 4 | B34: Gazdasági ügyek | C34: Közterületek takarításának költségei, közutak, járdák felújítása és fenntartása, vásárcsarnok és piac üzemeltetése, hatósági állatorvosi feladatok ellátása
A35: 411 | B35: Általános gazdasági és kereskedelmi ügyek | C35: Zajmérési vizsgálatok
A36: 41170 | B36: Műszaki vizsgálat, elemzés | C36: Zajmérési vizsgálatok
A37: 412 | B37: Általános munkaügyek | C37: Közterületek takarításának költségei
... A51: 7 | B51: Egészségügy | C51: Az egészségügyi kiadások nagy része a Terézvárosi Egészségügyi Szolgálat (TESZ) működtetése: járóbeteg-ellátás, szakorvosi ellátás, védőnői szolgálat, fogorvosi ellátás.
A52: 721 | B52: Általános orvosi szolgáltatások
A53: 72111 | B53: Háziorvosi alapellátás
A54: 72112 | B54: Háziorvosi ügyeleti ellátás
A55: 722 | B55: Szakosított orvosi szolgáltatások
A56: 72210 | B56: Járóbetegek gyógyító szakellátása
A57: 72220 | B57: Járóbetegek rehabilitációs szakellátása
A58: 72230 | B58: Járóbetegek gyógyító gondozása
A59: 723 | B59: Fogorvosi szolgáltatások
A60: 72311 | B60: Fogorvosi alapellátás
A61: 724 | B61: Paramedikális szolgáltatások
A62: 72410 | B62: Otthoni (egészségügyi) szakápolás
A63: 72420 | B63: Egészségügyi laboratóriumi szolgáltatások
... A70: 74040 | B70: Fertőző megbetegedések megelőzése, járványügyi ellátás
A71: 8 | B71: Szabadidő | C71: Eötvös10 Kulturális Színtér működtetése, Terézváros magazin fenntartása és egyéb lakossági tájékoztatási feladatok ellátása, civil és egyházi szervezetek támogatása, önkormányzat fenntartásában működő siófoki üdülő és dunabogdányi nyári tábor és erdei iskola működtetése.
A72: 810 | B72: Szabadidős és sportszolgáltatások | C72: Önkormányzat fenntartásában működő siófoki üdülő és dunabogdányi nyári tábor és erdei iskola működtetése
A73: 81071 | B73: Üdülői szálláshely-szolgáltatás és étkeztetés | C73: Önkormányzat fenntartásában működő üdülők és dunabogdányi nyári tábor és erdei iskola működtetése
A74: 820 | B74: Kulturális szolgáltatások | C74: Eötvös10 Kulturális Színtér működtetése
A75: 82092 | B75: Közművelődés - hagyományos közösségi kulturális értékek gondozása | C75: Eötvös10 Kulturális Színtér működtetése
A76: 830 | B76: Műsorszolgáltatási és kiadói szolgáltatások | C76: Terézváros magazin fenntartása és egyéb lakossági tájékoztatási feladatok ellátása
A77: 83030 | B77: Egyéb kiadói tevékenység | C77: Terézváros magazin fenntartása és egyéb lakossági tájékoztatási feladatok ellátása
A78: 83050 | B78: Televízió-műsor szolgáltatása és támogatása | C78: Egyéb lakossági tájékoztatási feladatok ellátása
A79: 840 | B79: Vallási és egyéb közösségi szolgáltatások | C79: Civil és egyházi szervezetek támogatása
A80: 84031 | B80: Civil szervezetek működési támogatása | C80: Civil és egyházi szervezetek támogatása
A81: 9 | B81: Oktatás | C81: Óvodák fenntartása, óvodai nevelés, gyermekétkeztetés kiadásai
A82: 911 | B82: Óvodai nevelés | C82: Az óvodák költségei, részletesen a közgazdasági nézetben böngészhető.
A83: 91110 | B83: Óvodai nevelés, ellátás szakmai feladatai
A84: 91120 | B84: Sajátos nevelési igényű gyermekek óvodai nevelésének, ellátásának szakmai feladatai
A85: 91130 | B85: Nemzetiségi óvodai nevelés, ellátás szakmai feladatai
A86: 91140 | B86: Óvodai nevelés, ellátás működtetési feladatai
A87: 960 | B87: Oktatást kiegészítő szolgáltatások | C87: Gyermekétkeztetés kiadásai
A88: 96015 | B88: Gyermekétkeztetés köznevelési intézményben
A89: B1 | B89: Működési célú támogatások államháztartáson belülről | C89: Döntően a központi költségvetésből kapott, normatív alapon járó, feladatfinanszírozási és kiegészítő támogatások
A90: B11 | B90: Önkormányzatok működési támogatásai | C90: Döntően a központi költségvetésből a napi működés kötelező feladataira kapott, kötött felhasználású támogatások
A91: B1101 | B91: Önkormányzatok működésének általános támogatása | C91: A központi költségvetésből az önkormányzatok részére, pl. a hivatal működtetésére, településüzemeltetésre (zöldterület-gazdálkodás, közvilágítás, köztemetők) juttatott feladatalapú támogatás
A92: B110101 | B92: Polgármesteri hivatal működésének támogatása | C92: A központi költségvetésből a hivatal működésének támogatása
A93: B110102 | B93: Településüzemeltetés - zöldterület-gazdálkodás támogatása | C93: A központi költségvetésből a településüzemeltetés támogatása
A94: B110103 | B94: Településüzemeltetés - közutak támogatása | C94: A központi költségvetésből a településüzemeltetés támogatása
A95: B110104 | B95: Egyéb önkormányzati feladatok támogatása | C95: A központi költségvetésből az egyéb önkormányzati feladatok támogatása
A96: B1102 | B96: Önkormányzatok egyes köznevelési feladatainak támogatása | C96: A központi költségvetésből az önkormányzatok egyes köznevelési feladatainak, pl. óvodaműködtetés támogatására biztosított feladatalapú és kiegészítő támogatások
A97: B110201 | B97: Óvodaműködtetési támogatás | C97: Központi költségvetésből az óvodák működtetésének támogatása
A98: B110202 | B98: Az óvodákban foglalkoztatott pedagógusok átlagbéralapú támogatása | C98: Központi költségvetésből az óvodák működtetésének támogatása
A99: B110203 | B99: Kiegészítő támogatás a pedagógusok és a pedagógus szakképzettséggel rendelkező segítők minősítéséből adódó többletkiadásokhoz | C99: Központi költségvetésből az óvodák működtetésének támogatása
A100: B110204 | B100: Nemzetiségi pótlék | C100: Központi költségvetésből az óvodák működtetésének támogatása
... A115: B24 | B115: Idegenforgalmi adó | C115: Helyi adó, amelyet a kerületben eltöltött vendégéjszakák után személyenként kell megfizetni
A116: B25 | B116: Egyéb közhatalmi bevételek (díjak, bírságok, közterület átengedése )
A117: B3 | B117: Működési bevételek és átvett pénzeszközök | C117: Olyan működéshez köthető bevételek, amelyek nem tartoznak a támogatások, az adóbevételek közé, és nem értékesítésből származnak (például parkolási bevételek, az üzlethelységek, lakások bérleti díja, járóbeteg-ellátáshoz kapott központi támogatás).
A118: B31 | B118: Nyújtott szolgáltatás ellenértéke | C118: Nyújtott szolgáltatásokért elsősorban a költségvetési szervek tesznek szert bevételre. Így jut bevételhez például a Terézvárosi Egészségügyi Szolgálat a díjköteles egészségügyi szolgáltatásokért.
A119: B32 | B119: Közvetített szolgáltatások ellenértéke | C119: A közvetített szolgáltatásokért jellemzően a Belső-Pesti Tankerületi Központ fizet az önkormányzatnak
A120: B33 | B120: Tulajdonosi bevételek | C120: Parkolásüzemeltetésből, lakások és helyiségek bérleti díjából, közterülethasználati díjból származó önkormányzati bevételek
A121: B3301 | B121: Parkolási bevétel a fővárosi területeken | C121: A fővárosi tulajdonú közterületeken is a kerületek üzemeltetik a parkolóhelyeket, de a parkolásból származó bevételek – a kerületi költségek levonása után – a fővárosi önkormányzatot illetik. A kerületnek a feladat ellátásából származó bevétele és kiadása ugyanakkora összeget tesz ki. Ez az összeg a kiadások között is megjelenik.
A122: B3302 | B122: Önkormányzati vagyon haszonbérbe adása (parkolás)
A123: B3303 | B123: Lakásbérletidíj-bevétel | C123: Az önkormányzat tulajdonában álló lakások bérbeadásából származó bérleti díjak
A124: B3304 | B124: Vagyonkezelő bérbeadás | C124: Bérleti jog átadásból származó bevételek a Vagyonkezelőnél.
A125: B3305 | B125: Piacüzemeltetésből származó bevétel
A126: B3306 | B126: Egyéb tulajdonnal összefüggő bevétel (víz, csatorna, szemét)
A127: B34 | B127: Ellátási díjak | C127: Bölcsődékben, óvodákban, iskolákban az étkezésért fizetett díjakból származó bevételek. Az étkezésért az azt igénybe vevők kb. 60%-a fizet, a többiek ingyenesen vagy kedvezményesen étkeznek.
A128: B35 | B128: Kiszámlázott általános forgalmi adó | C128: A tulajdonosi bevételek (például helyiség-bérbeadásból származó bevételek) áfája
A129: B36 | B129: Általános forgalmi adó visszatérítése | C129: Az önkormányzati áfás kiadások után visszaigényelhető összeg (például étkeztetés, közüzemi díjak áfája esetében)
A130: B37 | B130: Kamatbevételek | C130: Az államkötvényben tartott befektetésekből származó kamatbevételek
A131: B38 | B131: Egyéb működési bevételek | C131: Késedelmi kamatokból származó bevétel (ingatlanbérleti díjak után)
A132: B39 | B132: Működési célú átvett pénzeszközök | C132: Járóbeteg-ellátáshoz kapott központi támogatás
A133: B4 | B133: Felhalmozási bevételek, támogatások, átvett pénzeszközök | C133: Ingatlanok értékesítése, fejlesztésre kapott állami támogatások, nyújtott kölcsönök visszatérülése.
...

Sheet tooltips 2023
A1: Azon. | B1: Megnevezés | C1: Súgószöveg
A2: 1 | B2: Általános közszolgáltatások | C2: Az általános közszolgáltatások több, mint fele az önkormányzat vagyonának megőrzéséhez és fejlesztéséhez kapcsolódó kiadások, illetve a hivatal és az önkormányzati intézmények működtetése, döntéshozatala, igazgatása.
A3: 10 | B3: Szociális védelem | C3: A bölcsődei, család- és gyermekjóléti szolgáltatások, segélyek, ellátások, támogatások.
A4: 1011 | B4: Betegség
A5: 101110 | B5: Bentlakásos, nem kórházi ellátás, ápolás
A6: 101121 | B6: Pszichiátriai betegek tartós bentlakásos ellátása
A7: 101122 | B7: Szenvedélybetegek tartós bentlakásos ellátása
A8: 101123 | B8: Pszichiátriai betegek rehabilitációs célú bentlakásos ellátása
A9: 101124 | B9: Szenvedélybetegek rehabilitációs célú bentlakásos ellátása
A10: 101125 | B10: Pszichiátriai betegek rehabilitációs lakóotthoni ellátása
A11: 101126 | B11: Szenvedélybetegek rehabilitációs lakóotthoni ellátása
A12: 101131 | B12: Pszichiátriai betegek átmeneti ellátása
A13: 101132 | B13: Szenvedélybetegek átmeneti ellátása
A14: 101133 | B14: Támogatott lakhatás pszichiátriai betegek részére
A15: 101134 | B15: Támogatott lakhatás szenvedélybetegek részére
... A21: 101150 | B21: Betegséggel kapcsolatos pénzbeli ellátások, támogatások
A22: 1012 | B22: Fogyatékosság | C22: TERÉZÉNO fenntartása
A23: 101211 | B23: Fogyatékossággal élők tartós bentlakásos ellátása
A24: 101212 | B24: Fogyatékossággal élők rehabilitációs célú bentlakásos ellátása
A25: 101213 | B25: Fogyatékossággal élők átmeneti ellátása
A26: 101214 | B26: Támogatott lakhatás fogyatékos személyek részére
A27: 101215 | B27: Fogyatékossággal élők ápoló-gondozó lakóotthoni ellátása
A28: 101216 | B28: Fogyatékossággal élők rehabilitációs célú lakóotthoni ellátása
A29: 101221 | B29: Fogyatékossággal élők nappali ellátása | C29: TERÉZÉNO fenntartása
A30: 101222 | B30: Támogató szolgáltatás fogyatékos személyek részére
A31: 101231 | B31: Fogyatékossággal összefüggő pénzbeli ellátások, támogatások
A32: 101232 | B32: Megváltozott munkaképességgel összefüggő pénzbeli ellátások, támogatások
A33: 101240 | B33: Megváltozott munkaképességű személyek foglalkoztatását elősegítő képzések, támogatások
A34: 101270 | B34: Fogyatékossággal élők társadalmi integrációját és életminőségét segítő programok, támogatások
A35: 1020 | B35: Időskor, demens betegek | C35: TEGOSZ nyugdíjas klubjának fenntartása
A36: 102010 | B36: Nyugdíjbiztosítási szolgáltatások igazgatása
A37: 102023 | B37: Időskorúak tartós bentlakásos ellátása
A38: 102024 | B38: Demens betegek tartós bentlakásos ellátása
A39: 102025 | B39: Időskorúak átmeneti ellátása
A40: 102026 | B40: Demens betegek átmeneti ellátása
A41: 102030 | B41: Idősek, demens betegek nappali ellátása
A42: 102031 | B42: Idősek nappali ellátása | C42: TEGOSZ nyugdíjas klubjának fenntartása
A43: 102032 | B43: Demens betegek nappali ellátása
A44: 102040 | B44: Időskorral összefüggő pénzbeli ellátások
A45: 102050 | B45: Az időskorúak társadalmi integrációját célzó programok
A46: 1030 | B46: Túlélő hozzátartozók
A47: 103010 | B47: Elhunyt személyek hátramaradottainak pénzbeli ellátásai
A48: 1040 | B48: Család és gyermekek | C48: A bölcsődék és a családsegítő központ fenntartása, különböző gyermekvédelmi, család- és gyermekjóléti, családtámogatási ellátások, juttatások.
A49: 104011 | B49: Gyermekvédelmi bentlakásos ellátások
A50: 104012 | B50: Gyermekek átmeneti ellátása | C50: Terézvárosi Család- és Gyermekjóléti Központ tevékenysége.
A51: 104013 | B51: Nevelőszülőnél elhelyezettek ellátása
A52: 104020 | B52: Javítóintézeti ellátás
A53: 104030 | B53: Gyermekek napközbeni ellátása
A54: 104031 | B54: Gyermekek bölcsődei ellátása
A55: 104035 | B55: Gyermekétkeztetés bölcsődében, fogyatékosok nappali intézményében
A56: 104036 | B56: Munkahelyi étkeztetés bölcsődében
A57: 104037 | B57: Intézményen kívüli gyermekétkeztetés
A58: 104041 | B58: Területi gyermekvédelmi szakszolgáltatás
A59: 104042 | B59: Család és gyermekjóléti szolgáltatások
A60: 104043 | B60: Család és gyermekjóléti központ
A61: 104044 | B61: Biztos Kezdet Gyerekház
A62: 104051 | B62: Gyermekvédelmi pénzbeli és természetbeni ellátások
... A71: 106020 | B71: Lakásfenntartással, lakhatással összefüggő ellátások
A72: 1070 | B72: Egyéb szociális kirekesztettség | C72: Terézvárosi Gondozó Szolgálat (TEGOSZ) fenntartása, szociális étkeztetés, házi segítségnyújtás, jelzőrendszeres házi segítségnyújtás
A73: 107011 | B73: Hajléktalanok tartós bentlakásos ellátása
A74: 107012 | B74: Hajléktalanok rehabilitációs célú bentlakásos ellátása
A75: 107013 | B75: Hajléktalanok átmeneti ellátása
A76: 107014 | B76: Támogatott lakhatás hajléktalan személyek részére
A77: 107015 | B77: Hajléktalanok nappali ellátása
A78: 107016 | B78: Utcai szociális munka
A79: 107020 | B79: Családon belüli erőszak sértettjeinek bentlakásos ellátása
A80: 107030 | B80: Szociális foglalkoztatás
A81: 107051 | B81: Szociális étkeztetés
A82: 107052 | B82: Házi segítségnyújtás
A83: 107053 | B83: Jelzőrendszeres házi segítségnyújtás
A84: 107054 | B84: Családsegítés
... A96: 109070 | B96: Nemzetközi humanitárius segítségnyújtás
A97: 111 | B97: Államhatalmi, törvényhozó és végrehajtó szervezetek | C97: Az önkormányzat és az önkormányzati hivatal jogalkotó és általános igazgatási tevékenysége, ideértve a nemzetiségi önkormányzatok igazgatását is.
A98: 11110 | B98: Államhatalmi szervek tevékenysége
A99: 11120 | B99: Kormányzati igazgatási tevékenység
A100: 11130 | B100: Önkormányzatok és önkormányzati hivatalok jogalkotó és általános igazgatási tevékenysége | C100: A Polgármesteri Hivatal kiadásai, a képviselők és választott tisztségviselők juttatásai, a polgármesteri tisztséggel összefüggő egyéb kiadások.
A101: 11140 | B101: Országos és helyi nemzetiségi önkormányzatok igazgatási tevékenysége
A102: 112 | B102: Pénzügyi és költségvetési tevékenységek, adózási ügyek
A103: 11210 | B103: Az államháztartás igazgatása, ellenőrzése
A104: 11220 | B104: Adó-, vám- és jövedéki igazgatás | C104: A Hivatal adóügyi osztályának működése.
A105: 11230 | B105: Államadósság kezelése
A106: 113 | B106: Külügyek
A107: 11310 | B107: Külügyek igazgatása
A108: 11320 | B108: Nemzetközi szervezetekben való részvétel
A109: 121 | B109: Gazdasági segítség nyújtása fejlődő és átmeneti gazdaságú országoknak
A110: 12110 | B110: Gazdasági segítség nyújtása fejlődő és átmeneti gazdaságú országoknak
A111: 122 | B111: Gazdasági segítség nyújtása nemzetközi szervezeteken keresztül
A112: 12210 | B112: Gazdasági segítség nyújtása nemzetközi szervezeteken keresztül
A113: 131 | B113: Általános személyzeti szolgáltatások
A114: 13110 | B114: A közszolgálat egyetemes humánerő-gazdálkodása
A115: 132 | B115: Átfogó tervezési és statisztikai szolgáltatások
A116: 13210 | B116: Átfogó tervezési és statisztikai szolgáltatások
A117: 133 | B117: Egyéb általános szolgáltatások | C117: Vagyongazdálkodási kiadások, amelyek döntően a Vagyonkezelőhöz kötődnek.
A118: 13320 | B118: Köztemető-fenntartás és -működtetés
A119: 13330 | B119: Pályázat- és támogatáskezelés, ellenőrzés
A120: 13340 | B120: Az állami vagyonnal való gazdálkodással kapcsolatos feladatok
A121: 13350 | B121: Az önkormányzati vagyonnal való gazdálkodással kapcsolatos feladatok | C121: Döntően a Vagyonkezelő Zrt. különböző tevékenységeinek kiadásai (karbantartás, javítás, projektmenedzsment, önkormányzati tulajdon után fizetett közös költség stb.)
A122: 13360 | B122: Más szerv részére végzett pénzügyi-gazdálkodási, üzemeltetési, egyéb szolgáltatások
A123: 13370 | B123: Informatikai fejlesztések, szolgáltatások
A124: 13390 | B124: Egyéb kiegészítő szolgáltatások
...

Sheet tooltips 2024
A1: Azon. | B1: Megnevezés
A2: 1 | B2: Általános közszolgáltatások | C2: Az általános közszolgáltatások több, mint fele az önkormányzat vagyonának megőrzéséhez és fejlesztéséhez kapcsolódó kiadások, illetve a hivatal és az önkormányzati intézmények működtetése, döntéshozatala, igazgatása.
A3: 10 | B3: Szociális védelem | C3: A bölcsődei, család- és gyermekjóléti szolgáltatások, segélyek, ellátások, támogatások.
A4: 1012 | B4: Fogyatékosság | C4: TERÉZÉNO fenntartása
A5: 101221 | B5: Fogyatékossággal élők nappali ellátása | C5: TERÉZÉNO fenntartása
A6: 1020 | B6: Időskor, demens betegek | C6: TEGOSZ nyugdíjas klubjának fenntartása
A7: 102031 | B7: Idősek nappali ellátása | C7: TEGOSZ nyugdíjas klubjának fenntartása
A8: 1040 | B8: Család és gyermekek | C8: A bölcsődék és a családsegítő központ fenntartása, különböző gyermekvédelmi, család- és gyermekjóléti, családtámogatási ellátások, juttatások.
A9: 104012 | B9: Gyermekek átmeneti ellátása | C9: Terézvárosi Család- és Gyermekjóléti Központ tevékenysége.
A10: 1070 | B10: Egyéb szociális kirekesztettség | C10: Terézvárosi Gondozó Szolgálat (TEGOSZ) fenntartása, szociális étkeztetés, házi segítségnyújtás, jelzőrendszeres házi segítségnyújtás
A11: 111 | B11: Államhatalmi, törvényhozó és végrehajtó szervezetek | C11: Az önkormányzat és az önkormányzati hivatal jogalkotó és általános igazgatási tevékenysége, ideértve a nemzetiségi önkormányzatok igazgatását is.
A12: 11130 | B12: Önkormányzatok és önkormányzati hivatalok jogalkotó és általános igazgatási tevékenysége | C12: A Polgármesteri Hivatal kiadásai, a képviselők és választott tisztségviselők juttatásai, a polgármesteri tisztséggel összefüggő egyéb kiadások.
A13: 11220 | B13: Adó-, vám- és jövedéki igazgatás | C13: A Hivatal adóügyi osztályának működése.
... A27: 42180 | B27: Állat-egészségügy | C27: Hatósági állatorvosi feladatok ellátása
A28: 451 | B28: Közúti közlekedés | C28: Közutak, járdák felújítása és fenntartása
A29: 45160 | B29: Közutak, hidak, alagutak üzemeltetése, fenntartása | C29: Közutak, járdák felújítása és fenntartása
A30: 471 | B30: Elosztó kereskedelem, tárolás, raktározás | C30: Vásárcsarnok és piac üzemeltetése
A31: 47120 | B31: Piac üzemeltetése | C31: Vásárcsarnok és piac üzemeltetése
A32: 6 | B32: Közösségi létesítmények | C32: Társasházak felújítását szolgáló támogatások, városfejlesztéshez, városüzemeltetéshez kapcsolódó kiadások (például parkok, játszóterek fenntartása).
A33: 610 | B33: Lakásépítés | C33: Társasházak felújítását szolgáló támogatások
A34: 61030 | B34: Lakáshoz jutást segítő támogatások | C34: Társasházak felújítását szolgáló támogatások
A35: 660 | B35: Egyéb kommunális feladatok | C35: Városfejlesztéshez, városüzemeltetéshez kapcsolódó kiadások (például parkok, játszóterek fenntartása).
A36: 66010 | B36: Zöldterület-kezelés | C36: A zöldterületek fenntartásának, karbantartásának kiadásai
A37: 66020 | B37: Város-, községgazdálkodási egyéb szolgáltatások | C37: Városfejlesztéshez, városüzemeltetéshez kapcsolódó kiadások (például parkok, játszóterek fenntartása).
A38: 7 | B38: Egészségügy | C38: Az egészségügyi kiadások nagy része a Terézvárosi Egészségügyi Szolgálat (TESZ) működtetése: járóbeteg-ellátás, szakorvosi ellátás, védőnői szolgálat, fogorvosi ellátás.
A39: 8 | B39: Szabadidő | C39: Eötvös10 Kulturális Színtér működtetése, Terézváros magazin fenntartása és egyéb lakossági tájékoztatási feladatok ellátása, civil és egyházi szervezetek támogatása, önkormányzat fenntartásában működő siófoki üdülő és dunabogdányi nyári tábor és erdei iskola működtetése.
A40: 810 | B40: Szabadidős és sportszolgáltatások | C40: Önkormányzat fenntartásában működő siófoki üdülő és dunabogdányi nyári tábor és erdei iskola működtetése
... A52: B1 | B52: Működési célú támogatások államháztartáson belülről | C52: Döntően a központi költségvetésből kapott, normatív alapon járó, feladatfinanszírozási és kiegészítő támogatások
A53: B11 | B53: Önkormányzat központi működési támogatásai
A54: B1101 | B54: Önkormányzatok működésének általános támogatása | C54: A központi költségvetésből az önkormányzatok részére, pl. a hivatal működtetésére, településüzemeltetésre (zöldterület-gazdálkodás, közvilágítás, köztemetők) juttatott feladatalapú támogatás
A55: B110101 | B55: Önkormányzati Hivatal működésének állami támogatása
A56: B110102 | B56: Településüzemeltetés - zöldterület-gazdálkodás állami támogatása
A57: B110103 | B57: Településüzemeltetés - közutak állami támogatása
A58: B110104 | B58: Egyéb önkormányzati feladatok állami támogatása
A59: B110105 | B59: A 10 000 lakos feletti önkormányzatok energia áremelkedés miatti támogatása
A60: B1102 | B60: Önkormányzatok egyes köznevelési feladatainak támogatása | C60: A központi költségvetésből az önkormányzatok egyes köznevelési feladatainak, pl. óvodaműködtetés támogatására biztosított feladatalapú és kiegészítő támogatások
A61: B110201 | B61: Óvodaműködtetési támogatás | C61: Központi költségvetésből az óvodák működtetésének támogatása
A62: B110202 | B62: Az óvodákban foglalkoztatott pedagógusok átlagbéralapú támogatása | C62: Központi költségvetésből az óvodák működtetésének támogatása
A63: B110203 | B63: Kiegészítő támogatás a pedagógusok és a pedagógus szakképzettséggel rendelkező segítők minősítéséből adódó többletkiadásokhoz | C63: Központi költségvetésből az óvodák működtetésének támogatása
A64: B110204 | B64: Nemzetiségi pótlék | C64: Központi költségvetésből az óvodák működtetésének támogatása
A65: B110205 | B65: Az óvodákban foglalkoztatott pedagógusok nevelőmunkáját közvetlenül segítők átlagbéralapú támogatása | C65: Központi költségvetésből az óvodák működtetésének támogatása
A66: B110206 | B66: Diabétesz ellátási pótlék
A67: B1103 | B67: Önkormányzatok szociális gyermekjóléti és gyermekétkeztetési feladatainak támogatása | C67: A központi költségvetésből az önkormányzatok szociális, gyermekjóléti és gyermekétkeztetési feladatainak (ide értve a bölcsődéket) támogatására biztosított feladatalapú és kiegészítő támogatások
A68: B110301 | B68: Szociális és gyermekjóléti feladatok támogatása
A69: B11030101 | B69: Bölcsőde, mini bölcsőde támogatása | C69: A központi költségvetésből a bölcsődei bértámogatás és az üzemeltetés támogatása
A70: B11030102 | B70: Szociális szakosított ellátások, valamint a gyermekek átmeneti gondozásával kapcsolatos feladatok támogatása
A71: B11030103 | B71: Egyes szociális és gyermekjóléti feladatok támogatása | C71: A központi költségvetésből a család- és gyermekjóléti szolgálat, a házi segítségnyújtás, fogyatékosok nappali ellátásának támogatása
A72: B1103010301 | B72: Család- és gyermekjóléti szolgálat támogatása
A73: B1103010302 | B73: Család- és gyermekjóléti központ támogatása
A74: B1103010303 | B74: Szociális étkeztetés - önálló feladatellátás
A75: B1103010304 | B75: Szociális segítés (házi segítségnyújtás)
A76: B1103010305 | B76: Személyi gondozás - önálló feladatellátás (házi segítségnyújtás)
A77: B1103010306 | B77: Időskorúak nappali intézményi ellátása - önálló feladatellátás
A78: B1103010307 | B78: Fogyatékos személyek nappali intézményi ellátása -önálló feladatellátás
A79: B1103010308 | B79: Óvodai és iskolai szociális segítő tevékenység támogatása
A80: B110302 | B80: A települési önkormányzatok gyermekétkeztetési feladatainak támogatása | C80: A központi költségvetésből az intézményi gyermekétkeztetés támogatása
A81: B1104 | B81: Önkormányzatok kulturális feladatainak támogatása | C81: A központi költségvetésből az önkormányzatok könyvtári, közművelődési és múzeumi feladatainak támogatására biztosított feladatalapú és kiegészítő támogatások
A82: B12 | B82: Egyéb működési célú támogatások bevételei államháztartáson belülről | C82: A Nemzeti Egészségbiztosítási Alapkezelőtől (NEAK) egészségügyi és szociális feladatok ellátására érkező összeg. Ez az összeg a Terézvárosi Egészségügyi Szolgálat és a Terézvárosi Gondozó Szolgálat bevételeinek egy részét képezi.
A83: B2 | B83: Közhatalmi bevételek | C83: A lakosok és a helyi vállalatok által befizetett helyi adók, díjak, bírságok
A84: B21 | B84: Vagyoni típusú adók | C84: Építményadóból, telekadóból származó bevételek
A85: B2101 | B85: Építményadó | C85: Az építményadót a Terézvárosban lévő nem lakás céljára szolgáló épületek, épületrészek után kell fizetni. Rendeltetéstől, hasznosítástól függetlenül valamennyi helyiségre kiterjed az adókötelezettség. Az adó alapját a m2-ben számított hasznos alapterület adja.
A86: B2102 | B86: Telekadó | C86: A telekadót a Terézvárosban lévő telek, azaz épülettel, épületrésszel be nem épített földterület után kell fizetni. A telekadó alapját a telek m2-ben számított területe adja.
A87: B22 | B87: Iparűzési adó | C87: Az iparűzési adót a vállalkozások az önkormányzatnak fizetik be, Budapesten a fővárosi önkormányzatnak. Budapesten a befolyt teljes iparűzési adó bevétel 54%-a a fővárosi önkormányzaté, a maradék 46%-on pedig a kerületek osztoznak előre rögzített %-ok alapján, melyet a 26. évi CXXXIII. törvény rögzít. Minél több vállalkozás fizet Budapesten iparűzési adót, annál több lesz adott kerület iparűzési adó bevétele. A kerület iparűzési adó bevétele nem függ attól, hogy adott nagyvállalatnak abban a kerületben van-e a székhelye.
A88: B23 | B88: Gépjárműadó | C88: A kormány intézkedése szerint 2022 óta nem önkormányzati bevétel.
A89: B24 | B89: Idegenforgalmi adó | C89: Helyi adó, amelyet a kerületben eltöltött vendégéjszakák után személyenként kell megfizetni
A90: B25 | B90: Egyéb közhatalmi bevételek (díjak, bírságok, közterület átengedése )
A91: B2501 | B91: Közterület-használat, parkolás
A92: B250101 | B92: Közterület-használat átengedése
A93: B250102 | B93: Közutak nem közlekedési célú igénybevételéért fizetett díj
A94: B250103 | B94: Parkolóhelyek kizárólagos átengedése szerződés alapján
A95: B250104 | B95: Parkolóházakkal kötött megállapodások alapján
A96: B250105 | B96: Filmforgatás
A97: B250106 | B97: Podmaniczky utcai konténertároló
A98: B2502 | B98: Bírságok, díjak
A99: B250201 | B99: Helyi adópótlék, adóbírság
A100: B250202 | B100: Környezetvédelmi bírság
A101: B250203 | B101: Parkolóhely megváltás
... A108: B250210 | B108: Közigazgatási bírság
A109: B3 | B109: Működési bevételek és átvett pénzeszközök | C109: Olyan működéshez köthető bevételek, amelyek nem tartoznak a támogatások, az adóbevételek közé, és nem értékesítésből származnak (például parkolási bevételek, az üzlethelységek, lakások bérleti díja, járóbeteg-ellátáshoz kapott központi támogatás).
A110: B31 | B110: Nyújtott szolgáltatás ellenértéke | C110: Nyújtott szolgáltatásokért elsősorban a költségvetési szervek tesznek szert bevételre. Így jut bevételhez például a Terézvárosi Egészségügyi Szolgálat a díjköteles egészségügyi szolgáltatásokért.
A111: B32 | B111: Közvetített szolgáltatások ellenértéke | C111: A közvetített szolgáltatásokért jellemzően a Belső-Pesti Tankerületi Központ fizet az önkormányzatnak
A112: B33 | B112: Tulajdonosi bevételek | C112: Parkolásüzemeltetésből, lakások és helyiségek bérleti díjából, közterülethasználati díjból származó önkormányzati bevételek
A113: B3301 | B113: Helyiség bérleti díj bevétel (uszoda)
A114: B3302 | B114: Önkormányzati vagyon haszonbérbe adása (parkolás)
A115: B3303 | B115: Lakásbérletidíj-bevétel (Vagyonkezelő)
A116: B3304 | B116: Bérbeadás, bérleti jog átadás (Vagyonkezelő)
A117: B3305 | B117: Piacüzemeltetésből származó bevétel (Vagyonkezelő)
A118: B34 | B118: Ellátási díjak | C118: Bölcsődékben, óvodákban, iskolákban az étkezésért fizetett díjakból származó bevételek. Az étkezésért az azt igénybe vevők kb. 6%-a fizet, a többiek ingyenesen vagy kedvezményesen étkeznek.
A119: B35 | B119: Kiszámlázott általános forgalmi adó | C119: A tulajdonosi bevételek (például helyiség-bérbeadásból származó bevételek) áfája
A120: B36 | B120: Általános forgalmi adó visszatérítése | C120: Az önkormányzati áfás kiadások után visszaigényelhető összeg (például étkeztetés, közüzemi díjak áfája esetében)
A121: B37 | B121: Kamatbevételek | C121: Az államkötvényben tartott befektetésekből származó kamatbevételek
A122: B38 | B122: Egyéb működési bevételek | C122: Késedelmi kamatokból származó bevétel (ingatlanbérleti díjak után)
A123: B4 | B123: Felhalmozási bevételek, támogatások, átvett pénzeszközök | C123: Ingatlanok értékesítése, fejlesztésre kapott állami támogatások, nyújtott kölcsönök visszatérülése.
A124: B41 | B124: Ingatlanok értékesítése
A125: B4101 | B125: Kossuth u.
A126: B4102 | B126: 8647 Balatonmáriafürdő, Mária u. 40-41. (Hrsz:1291/1)
A127: B4103 | B127: 45 db pincei helyiség
A128: B44 | B128: Felhalmozási célú átvett pénzeszközök (társasházak)
A129: B5 | B129: Finanszírozási bevételek | C129: Az előző évi maradványok, lejárt betétekből származó bevétel.
A130: B51 | B130: Belföldi értékpapírok bevételei | C130: Értékpapírok beváltásából származó bevétel.
...

Sheet tooltips 2025
A1: Megnevezés | B1: Azon. | C1: Súgószöveg
A2: Személyi juttatások és járulékok | B2: K1 | C2: =VLOOKUP(B2,'tooltips 2024'!A:C,3) -> Személyi kiadások és a munkáltató által fizetett járulékaik
A3: Önkormányzat személyi juttatásai és járulékai | B3: K11 | C3: =VLOOKUP(B3,'tooltips 2024'!A:C,3) -> Személyi kiadások és a munkáltató által fizetett járulékaik
A4: Külső személyi juttatások | B4: K1102 | C4: =VLOOKUP(B4,'tooltips 2024'!A:C,3) -> Feladatot ellátó, nem foglalkoztatotti viszonyban lévő személyek juttatásai
A5: Munkaadókat terhelő járulékok és szociális hozzájárulási adó | B5: K1103 | C5: =VLOOKUP(B5,'tooltips 2024'!A:C,3)
A6: Polgármesteri Hivatal személyi juttatásai és járulékai | B6: K12 | C6: =VLOOKUP(B6,'tooltips 2024'!A:C,3) -> Személyi kiadások és a munkáltató által fizetett járulékaik
A7: Foglalkoztatottak személyi juttatásai | B7: K1201 | C7: =VLOOKUP(B7,'tooltips 2024'!A:C,3) -> Foglalkoztatotti viszonyban lévők személyi juttatásai.
A8: Külső személyi juttatások | B8: K1202 | C8: =VLOOKUP(B8,'tooltips 2024'!A:C,3) -> Feladatot ellátó, nem foglalkoztatotti viszonyban lévő személyek juttatásai
A9: Munkaadókat terhelő járulékok és szociális hozzájárulási adó | B9: K1203 | C9: =VLOOKUP(B9,'tooltips 2024'!A:C,3)
A10: Óvodák személyi juttatásai és járulékai | B10: K13 | C10: =VLOOKUP(B10,'tooltips 2024'!A:C,3) -> Személyi kiadások és a munkáltató által fizetett járulékaik
A11: Fasori óvoda személyi juttatásai és járulékai | B11: K1301 | C11: =VLOOKUP(B11,'tooltips 2024'!A:C,3) -> Személyi kiadások és a munkáltató által fizetett járulékaik
A12: Foglalkoztatottak személyi juttatásai | B12: K130101 | C12: =VLOOKUP(B12,'tooltips 2024'!A:C,3) -> Foglalkoztatotti viszonyban lévők személyi juttatásai.
A13: Külső személyi juttatások | B13: K130102 | C13: =VLOOKUP(B13,'tooltips 2024'!A:C,3) -> Feladatot ellátó, nem foglalkoztatotti viszonyban lévő személyek juttatásai
... A34: Munkaadókat terhelő járulékok és szociális hozzájárulási adó | B34: K1403 | C34: =VLOOKUP(B34,'tooltips 2024'!A:C,3)
A35: Terézvárosi Értelmi Fogyatékosok Napközi Otthona személyi juttatásai és járulékai | B35: K15
A36: Foglalkoztatottak személyi juttatásai | B36: K1501 | C36: =VLOOKUP(B36,'tooltips 2024'!A:C,3) -> Foglalkoztatotti viszonyban lévők személyi juttatásai.
A37: Külső személyi juttatások | B37: K1502 | C37: =VLOOKUP(B37,'tooltips 2024'!A:C,3) -> Feladatot ellátó, nem foglalkoztatotti viszonyban lévő személyek juttatásai
A38: Munkaadókat terhelő járulékok és szociális hozzájárulási adó | B38: K1503 | C38: =VLOOKUP(B38,'tooltips 2024'!A:C,3)
A39: Terézvárosi Gondozó Szolgálat személyi juttatásai és járulékai | B39: K16
A40: Foglalkoztatottak személyi juttatásai | B40: K1601 | C40: =VLOOKUP(B40,'tooltips 2024'!A:C,3) -> Foglalkoztatotti viszonyban lévők személyi juttatásai.
A41: Külső személyi juttatások | B41: K1602 | C41: =VLOOKUP(B41,'tooltips 2024'!A:C,3) -> Feladatot ellátó, nem foglalkoztatotti viszonyban lévő személyek juttatásai
A42: Munkaadókat terhelő járulékok és szociális hozzájárulási adó | B42: K1603 | C42: =VLOOKUP(B42,'tooltips 2024'!A:C,3)
A43: Terézvárosi Család- és Gyermekjóléti Központ személyi juttatásai és járulékai | B43: K17
A44: Foglalkoztatottak személyi juttatásai | B44: K1701 | C44: =VLOOKUP(B44,'tooltips 2024'!A:C,3) -> Foglalkoztatotti viszonyban lévők személyi juttatásai.
A45: Külső személyi juttatások | B45: K1702 | C45: =VLOOKUP(B45,'tooltips 2024'!A:C,3) -> Feladatot ellátó, nem foglalkoztatotti viszonyban lévő személyek juttatásai
A46: Munkaadókat terhelő járulékok és szociális hozzájárulási adó | B46: K1703 | C46: =VLOOKUP(B46,'tooltips 2024'!A:C,3)
A47: Terézvárosi Egyesített Bölcsődék személyi juttatásai és járulékai | B47: K18
A48: Foglalkoztatottak személyi juttatásai | B48: K1801 | C48: =VLOOKUP(B48,'tooltips 2024'!A:C,3) -> Foglalkoztatotti viszonyban lévők személyi juttatásai.
A49: Külső személyi juttatások | B49: K1802 | C49: =VLOOKUP(B49,'tooltips 2024'!A:C,3) -> Feladatot ellátó, nem foglalkoztatotti viszonyban lévő személyek juttatásai
A50: Munkaadókat terhelő járulékok és szociális hozzájárulási adó | B50: K1803 | C50: =VLOOKUP(B50,'tooltips 2024'!A:C,3)
A51: Dologi kiadások | B51: K2 | C51: =VLOOKUP(B51,'tooltips 2024'!A:C,3) -> A mindennapi működéshez, a feladatok ellátásához szükséges kiadások
A52: Önkormányzat dologi kiadásai | B52: K21 | C52: =VLOOKUP(B52,'tooltips 2024'!A:C,3) -> A mindennapi működéshez, a feladatok ellátásához szükséges kiadások
A53: Készletbeszerzés | B53: K2101 | C53: =VLOOKUP(B53,'tooltips 2024'!A:C,3) -> Működtetéshez szükséges eszközök, például nyomtatványok, irodaszerek beszerzésére fordított összeg
A54: Kommunikációs szolgáltatások | B54: K2102 | C54: =VLOOKUP(B54,'tooltips 2024'!A:C,3) -> Távközlési díjak (internet, telefon), honlapfejlesztés, videókészítés
A55: Szolgáltatási kiadások | B55: K2103 | C55: =VLOOKUP(B55,'tooltips 2024'!A:C,3) -> A dologi kiadások tetemes részét szolgáltatások vásárlására költi az önkormányzat. Ilyenek például: lakóépületek karbantartása, közös költség fizetés, étkeztetés, bérleti jogviszony megváltása
A56: Kiküldetés | B56: K2104
A57: Különféle befizetések és dologi kiadások | B57: K2105 | C57: =VLOOKUP(B57,'tooltips 2024'!A:C,3) -> Legnagyobb tétele az önkormányzat által kifizetett áfa
A58: Polgármesteri Hivatal dologi kiadásai | B58: K22 | C58: =VLOOKUP(B58,'tooltips 2024'!A:C,3) -> A mindennapi működéshez, a feladatok ellátásához szükséges kiadások
A59: Készletbeszerzés | B59: K2201 | C59: =VLOOKUP(B59,'tooltips 2024'!A:C,3) -> Működtetéshez szükséges eszközök, például nyomtatványok, irodaszerek beszerzésére fordított összeg
A60: Kommunikációs szolgáltatások | B60: K2202 | C60: =VLOOKUP(B60,'tooltips 2024'!A:C,3) -> Távközlési díjak (internet, telefon), honlapfejlesztés, videókészítés
A61: Szolgáltatási kiadások | B61: K2203 | C61: =VLOOKUP(B61,'tooltips 2024'!A:C,3) -> A dologi kiadások tetemes részét szolgáltatások vásárlására költi az önkormányzat. Ilyenek például: lakóépületek karbantartása, közös költség fizetés, étkeztetés, bérleti jogviszony megváltása
A62: Kiküldetés, reklám | B62: K2204
A63: Különféle befizetések és dologi kiadások | B63: K2205 | C63: =VLOOKUP(B63,'tooltips 2024'!A:C,3) -> Legnagyobb tétele az önkormányzat által kifizetett áfa
A64: Óvodák dologi kiadásai | B64: K23 | C64: =VLOOKUP(B64,'tooltips 2024'!A:C,3) -> A mindennapi működéshez, a feladatok ellátásához szükséges kiadások
A65: Fasori óvoda dologi kiadásai | B65: K2301 | C65: =VLOOKUP(B65,'tooltips 2024'!A:C,3) -> A mindennapi működéshez, a feladatok ellátásához szükséges kiadások
A66: Játékvár óvoda dologi kiadásai | B66: K2302 | C66: =VLOOKUP(B66,'tooltips 2024'!A:C,3) -> A mindennapi működéshez, a feladatok ellátásához szükséges kiadások
A67: Szív óvoda dologi kiadásai | B67: K2303 | C67: =VLOOKUP(B67,'tooltips 2024'!A:C,3) -> A mindennapi működéshez, a feladatok ellátásához szükséges kiadások
A68: Mesevilág óvoda dologi kiadásai | B68: K2304 | C68: =VLOOKUP(B68,'tooltips 2024'!A:C,3) -> A mindennapi működéshez, a feladatok ellátásához szükséges kiadások
A69: Kincseskert óvoda dologi kiadásai | B69: K2305 | C69: =VLOOKUP(B69,'tooltips 2024'!A:C,3) -> A mindennapi működéshez, a feladatok ellátásához szükséges kiadások
A70: Terézvárosi Egészségügyi Szolgálat dologi kiadásai | B70: K24 | C70: =VLOOKUP(B70,'tooltips 2024'!A:C,3) -> A mindennapi működéshez, a feladatok ellátásához szükséges kiadások
A71: Terézvárosi Értelmi Fogyatékosok Napközi Otthona dologi kiadásai | B71: K25 | C71: =VLOOKUP(B71,'tooltips 2024'!A:C,3) -> A mindennapi működéshez, a feladatok ellátásához szükséges kiadások
A72: Terézvárosi Gondozó Szolgálat dologi kiadásai | B72: K26 | C72: =VLOOKUP(B72,'tooltips 2024'!A:C,3) -> A mindennapi működéshez, a feladatok ellátásához szükséges kiadások
A73: Terézvárosi Család- és Gyermekjóléti Központ dologi kiadásai | B73: K27 | C73: =VLOOKUP(B73,'tooltips 2024'!A:C,3) -> A mindennapi működéshez, a feladatok ellátásához szükséges kiadások
A74: Terézvárosi Egyesített Bölcsődék dologi kiadásai | B74: K28 | C74: =VLOOKUP(B74,'tooltips 2024'!A:C,3) -> A mindennapi működéshez, a feladatok ellátásához szükséges kiadások
A75: Ellátottak pénzbeli juttatásai | B75: K3 | C75: =VLOOKUP(B75,'tooltips 2024'!A:C,3) -> Az önkormányzat szociális támogatásai. A széleskörű támogatási rendszerben vannak havi rendszerességgel és eseti jelleggel nyújtott támogatások is. A szociális juttatások legnagyobb tételei: az idősek világnapjára adott juttatás, az eseti támogatás, a lakhatási támogatás, a fűtéstámogatás és a gyógyszertámogatás.
A76: Települési támogatás formájában, havi rendszerességgel nyújtott támogatások | B76: K31
A77: Ápolási támogatás | B77: K3101
A78: Fogyatékos/vak személy támogatása | B78: K3102
A79: Tartósan beteg vagy fogyatékossággal élő magasabb családi pótlékra jogosult gyermekek támogatása (15.000 Ft/hó/fő) | B79: K3103
A80: Fűtéstámogatás | B80: K3104
A81: Gyógyszertámogatás | B81: K3105
A82: Hátralékkiegyenlítő támogatás | B82: K3106
A83: Hátralékkiegyenlítő támogatáshoz nyújtott lakhatási támogatás | B83: K3107
A84: Terézvárosért kiemelten fontos munkát végzők lakbértámogatása | B84: K3108
A85: Lakhatási támogatás | B85: K3109
A86: Rendkívüli települési támogatások | B86: K32
A87: Egyszeri támogatás (Karácsonyi) | B87: K3201
... A101: Egyéb | B101: K34
A102: Egyéb működési célú kiadások | B102: K4 | C102: =VLOOKUP(B102,'tooltips 2024'!A:C,3) -> Az önkormányzati cégeknek, iskolai alapítványoknak, civil szervezeteknek, kerületi rendőrkapitányságnak nyújtott támogatások.
A103: Elvonások és befizetések | B103: K41 | C103: =VLOOKUP(B103,'tooltips 2024'!A:C,3) -> A központi költségvetésbe befizetendő szolidaritási hozzájárulás
A104: Egyéb működési célú támogatás államháztartáson belülre | B104: K42 | C104: =VLOOKUP(B104,'tooltips 2024'!A:C,3) -> Kerületi rendőrség és kerületi könyvtárak támogatása
A105: BRFK Térfigyelő rendszerrel és a járőrszolgálattal kapcsolatos feladatok | B105: K4201
A106: Közép-Pesti Katasztrófavédelmi Kirendeltség támogatása | B106: K4202
A107: Dunabogdányi önkormányzati fenntartású gyermeküdülőben erdei iskolában munkát végző pedagógusok díjazása | B107: K4203
A108: Könyvtárak támogatása, FSZEK | B108: K4204
A109: Egyéb működési célú támogatás államháztartáson kívülre | B109: K43 | C109: =VLOOKUP(B109,'tooltips 2024'!A:C,3) -> Nonprofit gazdasági társaságoknak, iskolai alapítványoknak, civil szervezeteknek, egyházaknak nyújtott működési célú támogatások
A110: Működési támogatás háztartások részére | B110: K4301
A111: Társasházi zöldfelület fejlesztés és tervezés áthúzódó | B111: K430101
A112: Társasházi zöldfelület fejlesztés új támogatás | B112: K430102
A113: Egyedi növényesítési igények társasházaknak, intézményeknek | B113: K430103
A114: Működési támogatás egyházak, civilek részére | B114: K4302
A115: Egyházak, egyházi jogi személyek támogatása | B115: K430201
A116: EKIF Boldog Adolf Kolping Katolikus Iskola Óvodája | B116: K43020101
A117: Egyházaknak támogatás | B117: K43020102
A118: Civil szervezetek támogatása (pályázati támogatás) | B118: K430202
A119: Hajlétalanokat ellátó intézmények téli felkészülésének támogatása (pályázat alapján) | B119: K430203
A120: TámogatLak program | B120: K430204
A121: Fenntartható kezdeményezések (pályázat) | B121: K430205
... A147: Terézvárosi Kulturális Közhasznú Nonprofit Zrt. támogatása | B147: K430401
A148: Terézvárosi Foglalkoztatást Elősegítő Nonprofit Kft. | B148: K430402 | C148: =VLOOKUP(B148,'tooltips 2024'!A:C,3) -> A közfeladatot ellátó társaság a kerület tartósan munkanélküli és rendszeres szociális ellátásban részesülő lakosainak kínál munkalehetőséget. Az itt dolgozók a közterületek takarítását, a játszóterek, kutyafuttatók, szökőkutak kezelését és a kertészeti munkálatokat végzik el.
A149: Tartalékok | B149: K44 | C149: =VLOOKUP(B149,'tooltips 2024'!A:C,3) -> A tartalékok azok a kiadások, amelyeknek a felhasználása év elején a költségvetés elfogadásakor még nem tudható pontosan, vagy a felhasználás feltételekhez kötött.
A150: Általános tartalék | B150: K4401 | C150: =VLOOKUP(B150,'tooltips 2024'!A:C,3) -> Nem konkrét célokra, hanem a gazdálkodás biztonsága érdekében nem várt kiadásokra félretett tartalék.
A151: Céltartalék | B151: K4402 | C151: =VLOOKUP(B151,'tooltips 2024'!A:C,3) -> Bérkiegészítésekre, kitüntetésekre, óvodai, iskolai támogatásokra, szociális és egyéb támogatásokra szolgáló tartalék
A152: Keretek, jutalmak | B152: K440201
A153: Polgármesteri keret | B153: K44020101
A154: Alpolgármesteri keret | B154: K44020102
A155: Rendőrségi dolgozók jutalma | B155: K44020103
A156: Lakossági tanfolyamok | B156: K44020104
A157: Polgármesteri elismerés pedagógusoknak "Kiemelkedő pedagógiai munkáért" | B157: K44020105
A158: Pedagógusdíjak, kitüntetések ("Terézváros közoktatásáért", jubileumi diplomák) | B158: K44020106
...

Sheet milestones
A1: nodeId | B1: year | C1: imageFile | D1: videoFile | E1: title | F1: descriptionInMarkdown | G1: tags | H1: pos | I1: onlyOnMap
B2: 2021 | C2: 2021-1.jpg | E2: Lakossági parkolóhelyeket alakítunk ki | F2: Terézváros önkormányzata a mostani parkolóhelyek közül közel 1400-at hamarosan kizárólagos használatra a VI. kerület lakóinak ad át az esti órákban. A táblával megjelölt helyeken 18 és reggel 7 óra között csak azok a helyi lakosok parkolhatnak majd, akik éves parkolási engedéllyel rendelkeznek. Az intézkedés lényege, hogy munkaidő után a parkolóhelyek a hazatérő terézvárosiak rendelkezésére álljanak. A terézvárosi parkolóhelyek kialakításával egyidőben felülvizsgáljuk a mozgássérült parkolóhelyek és a rakodóhelyek kijelölését is, hogy a speciális várokozóhelyek a valós igényekhez igazodjanak.
B3: 2021 | C3: 2021-2.jpg | E3: Közösségi tereket hozunk létre | F3: A Jókai tér a teljes megújítást követően méltó szomszédja lesz a világörökség részét képező Andrássy útnak. A teret határoló utcákról eltűnik a rossz állapotú macskakő, az új burkolat jóvoltából megszűnik a zaj, könnyebbé válik a közlekedés. A tér új zöldfelületet kap, de átlátható lesz, ez is biztosítja majd a rendet, tisztaságot. A térrel szomszédos utcákban megváltozik a parkolási rend is, azzal a céllal, hogy a gyalogosok biztonságosabban közlekedhessenek. A fővárosi önkormányzat által meghirdetett 2016-os TÉR-KÖZ városrehabilitációs pályázaton Terézváros önkormányzata 200 millió Ft támogatást nyert a tér rendezésére. A Podmaniczky utcai kutyafuttató idei felújítását tavaly már közösségi tervezés, több lakossági egyeztetés előzte meg. Mivel jelenleg ez a kerület egyetlen kutyafuttatója, fontos, hogy a gazdik és a kutyák számára is szép, rendezett, pihenésre alkalmas környezet jöjjön létre. A Rózsa utca 53. szám alatti önkormányzati tulajdonú telken egy ideiglenes közösségi kertet alakítunk ki, ahol a terézvárosiak kertészkedhetnek majd a kialakított parcellákban. A telek így nemcsak kizöldül, hanem fontos közösségi színtere is lehet a beszélgetéseknek, a szabadidő közös és hasznos eltöltésének. A Benczúr utcában pótoljuk a fasor fáit, bokrokat, cserjéket ültetünk, és ezzel párhuzamosan a járdákat is megújítjuk, hogy biztosítsuk ezzel a növények életterét és az akadálymentes közlekedést is. Tárgyalunk a Magyar Képzőművészeti Egyetem vezetésével, hogy a terület rendezésével az Epreskert egy részét megnyithassuk a terézvárosiak számára. _A költségvetésben rendelkezésre álló összegek:_ Jókai tér fejújítása: 510 millió Ft Podmaniczky utcai kutyafuttató megújítása: 15 millió Ft Rózsa utcai közösségi kert létrehozása: 20 millió Ft Benczúr utcai fasor megújítása, zöldsáv kialakítása: 46 millió Ft Epreskert megnyitása: 60 millió Ft
B4: 2021 | C4: 2021-3.jpg | E4: Megújítjuk a külső után a vásárcsarnok belső terét is | F4: Idén új szakaszához ér a Hunyadi téri vásárcsarnok felújítása. Tavaly a közösségi tervezés során megismertük a helyiek igényeit, most ezek alapján elkezdjük a csarnok belső tereinek tervezését. Az a célunk, hogy a belső átépítés figyelembe vegye a Czingler Győző által 1896-ban tervezett, és nemrégiben megújult külsőt. A csarnok tervezett megújításával párhuzamosan a Szófia utca is új szerephez juthat: a csarnokban működő vendéglátók teraszai újfajta pezsgést hozhatnak a környékre. _A költségvetésben rendelkezésre álló összeg:_ Vásárcsarnok felújításának tervezési munkája: 120 millió Ft
B5: 2021 | C5: 2021-4.jpg | E5: Növeljük a bérlakások számát | F5: Terézváros önkormányzata elkötelezett a lakhatási válság csökkentése mellett. A Terézváros otthont ad programban a lakásállomány folyamatos karbantartásával párhuzamosan idén húsz, eddig használaton kívüli önkormányzati bérlakást újítunk fel, ezekbe Terézvárosban élők és dolgozók (szolgálati lakások) költözhetnek majd be. A lakások korszerűsítésével párhuzamosan az Aradi utca 22. szám alatti bérház felújításának első szakasza is elindul, ezzel is tovább növeljük a bérlakásaink számát. Egy teljesen új önkormányzati fenntartású bérlakás-projekt is elindul egy új bérház tervezésének, építésének előkészítésével. _A költségvetésben rendelkezésre álló összegek:_ Húsz bérlakás felújítása: 110 millió Ft Aradi u. 22. - lakóépület felújítása: 265 millió Ft Bérház építésének előkészítése: 30 millió Ft
B6: 2021 | C6: 2021-5.jpg | E6: A Csengery utcában teljes körű megújítást végzünk fásítással | F6: Az önkormányzat már 2020-ban megkezdte a Csengery utca (Aradi és Podmaniczky utca közötti szakasz) teljes megújításának és ezzel párhuzamosan a fásítási munkáinak előkészítését. A tervezést megelőzve elkészült egy tanulmány, amely azt vizsgálta, hogyan lehet fákat ültetni a szűk, közműhálózattal átszőtt utcában. Több megoldási javaslat is született, melyet a lakók már megismerhettek, a végleges tervek is a terézvárosiak véleménye alapján fog megszületni. Az biztos, hogy a Csengery utca amellett, hogy igazi zöldfelületet kap, teljesen meg is újul. Az átalakításnak csak egy kis szelete a fásítás, emellett az utcaszakasz infrastruktúrája is átalakul: nő a járdák mérete, biztonságosabb lesz a közlekedés. _A költségvetésben rendelkezésre álló összeg:_ Közterület-megújítás, a Csengery utca, Aradi és Podmaniczky utca közötti teljes megújítása: 400 millió Ft
B7: 2021 | C7: 2021-6.jpg | E7: Magánberuházókkal közösen szépítjük meg a Paulay utcát | F7: A Paulay és a Hegedű utcában jelenleg egy időben több szálloda is épül. Az önkormányzat a beruházókkal településrendezési szerződést kötött, amelyben az építtetők vállalják, hogy a készülő hotel környékén nemcsak rendezik a keletkezett károkat, hanem rendbe teszik, megszépítik a közterületet. A Paulay utca 52-nél folyó építkezést követően az önkormányzat és a beruházó összefogásával átalakítjuk a terület Nagymező utca és Liszt Ferenc tér közötti részét. Zöld szigeteket alakítunk ki, ezzel is csillapítjuk a Paulay utca forgalmát. Az utcát a későbbiekben teljes hosszában felújítjuk a Hegedű utcával együtt, így élhetőbb, csendesebb, tisztább közterületeket kapnak az ott élők. _A költségvetésben rendelkezésre álló összegek:_ Paulay u., Hegedű u. és Liszt F. tér közötti szakaszán út- és járdaépítés: 30 millió Ft
B8: 2021 | C8: 2021-7.jpg | E8: Korszerűsítjük az egészségügyi és oktatási intézményeket | F8: Megújul idén a Tóth Aladár Zeneiskola és Szinyei Merse Pál Gimnázium Kmetty utcai külső homlokzata. Munkálatok folynak majd a Lendvay utcai Játékvár óvodában is, ahol az udvart újítjuk fel, a Bajza utcai Általános Iskolában pedig a tanuszoda fűtéskorszerűsítét végezzük el. A Terézvárosi Egészségügyi Szolgálat Csengery utcai épületében többek között megújul a hűtő-fűtő rendszer, kicseréljük az elavult gépeket, műszereket részben az Egészséges Budapest Program keretében. A gyermekfogászati rendelőben beléptető- és betegirányító rendszert alakítunk ki. _A költségvetésben rendelkezésre álló összegek:_ Tóth Aladár Zeneiskola homlokzatfelújítása: 100 millió Ft Játékvár óvoda udvarfelújítása: 65 millió Ft Bajza utcai Általános Iskola tanuszodájának fűtéskorszerűsítése: 25 millió Ft Szinyei Merse Pál Gimnázium homlokzatfelújítása: 70,6 millió Ft Terézvárosi Egészségügyi Szolgálat épületfelújítása, műszereinek korszerűsítése: 891 millió Ft
B9: 2021 | C9: 2021-8.jpg | E9: Fejlesztjük a környezetbarát közlekedés lehetőségeit | F9: A környezetbarát közlekedési eszközök népszerűsítése, valamint az elektromos rollerek kulturált elhelyezésének érdekében az önkormányzat a fővárossal közösen, több ütemben mikromobilitási pontokat hoz létre Belső-Terézvárosban. A jórészt forgalomtól elzárt területeken kialakítandó pontokon lehet majd biztonságosan elhelyezni a kerékpárokat, rollereket, robogókat. Ezeken a pontokon lesz az elektromos rollerek kötelező lerakata is. A projekt keretében a főváros a saját kezelésű területein 48, Terézváros önkormányzata pedig 38 ponton alakít ki mobilitási pontot. A mobilitási pontokkal összhangban elektromos töltőállomások kihelyezésének előkészítése is elindult, és új kerékpártámaszok kerülnek ki a kerületben. Hosszú évek problémájának megoldását szolgálja a Bajza és Bulcsú utcát összekötő aluljáró felújítása. A sok tulajdonos között az önkormányzatnak sikerült elérni az együttműködést: a MÁV, a fővárosi önkormányzat, valamint a kerületi önkormányzatok elkezdtek dolgozni a részfeladatokon, a tervek tavaszra készen lesznek, utána kezdődhet a kivitelezés. Az aluljáró megújítása után jelentős szerepet tölt majd be a kerékpáros közlekedési hálózatban. _A költségvetésben rendelkezésre álló összegek:_ Forgalomcsillapítás, mobilitási pontok kialakítása, kerékpártámaszok: 50 millió Ft Bajza-Bulcsú aluljáró megújítása zöldfelületekkel: 56 millió Ft
B10: 2021 | C10: 2021-9.jpg | E10: A koronavírus-járvány költségvetési hatásai | F10: A járvány és a nyomában járó gazdasági válság súlyos következményekkel járt az idegenforgalmáról, vendéglátásáról ismert Terézvárosban. A bezárt éttermek, szállodák, szórakozóhelyek miatt keletkező bevételkiesést azonban jóval meghaladta a kormányzati elvonás, amivel együtt Terézváros önkormányzata csaknem 3 milliárd forint bevételtől esik el. **Kormányzati elvonások:** iparűzési adó: 753 846 000 Ft gépjárműadó elvonása: 115 000 000 Ft központi támogatásként kirótt összeg: 674 326 000 Ft ingyenes parkolásból származó bevételkiesés: 520 000 000 Ft **Járvány gazdasági hatásai:** idegenforgalmi adó elmaradása: 600 000 000 Ft közterület foglalási díjak elmaradása: 200 000 000 Ft **Összesen: 2 863 172 000 Ft** Az elvonások, bevételcsökkenések ellenére is kötelességének érzi az önkormányzat, hogy segítse azokat, akik a járvány miatt kerültek nehéz anyagi helyezte. A Terézváros melléd áll! programmal az állás nélkül maradt magánszemélyek, és a munka nélkül maradt vállalkozások is segítséget kaptak, hogy talpon maradjanak és átvészeljék a nehéz hónapokat. Az önkormányzat szociális programja a diákokat is segíti azzal, hogy biztosítja a számítástechnikai hátteret az online tanuláshoz.
B11: 2022 | C11: 2022-1.jpg | E11: Megújuló, zöldülő utcák | F11: Elkötelezettek vagyunk a környezettudatos, fenntartható városi lét kialakításában, a közterületeink élhetőbbé tételében. Éppen ezért az elmúlt harminc év legnagyobb közterület-fejlesztését készülünk véghezvinni. Idén elkezdjük a Csengery utca megújítását, és további közterületek felújításának tervezését. Részleges vagy teljes utcamegújítás, zöldítés és forgalomcsillapítást készítünk elő a Szondi, a Szinyei Merse Pál, a Felsőerdősor, az Eötvös, a Szófia, a Rózsa, a Németh László, a Szobi, a Kármán, a Lovag, a Dobó, a Káldy Gyula, a Paulay Ede és a Zichy Jenő utcában, a Bajcsy-Zsilinszky és a Révay közben. Ezek tervezésénél az alternatív közlekedési formák, a forgalomcsillapítás, valamint a gyalogos- és zöldfelületek, közösségi terek maximalizálásán lesz a hangsúly. A kerület növényzettel legkevésbé ellátott területein, így a Szondi, a Szinyei Merse Pál, a Vörösmarty, a Csengery és az Eötvös utcában fásítást készítünk elő. Az Andrássy úti műfű korábbi helyére végre igazi, évelő növények kerülnek, amit a világörökségi területhez méltó ráccsal és emelt szegéllyel védünk majd a parkoló autóktól és a kutyavizelettől.
B12: 2022 | C12: 2022-2.jpg | E12: Parkolási káosz enyhítése | F12: Visszaadjuk a terézvárosiaknak a kerületi parkolóhelyek harmadát. Belső-Terézvárosban már használják az este 6 és reggel 7 közötti időtartamra szóló kizárólagos lakossági parkolóhelyeket, idén pedig Külső-Terézvárosban is megtörténik ezek kitáblázása. A kedvezményes parkolási engedéllyel rendelkező lakóknak így ezeken a területeken is könnyebb lesz parkolóhelyhez jutni. Az önkormányzat anyagi hozzájárulásával továbbra is kedvezményes áron juthatnak parkolóházi helyekhez a helyi lakosok. Hét parkolóházban a piaci árhoz képest 60-70 százalékos kedvezménnyel tudnak parkolni azok, akik cserébe lemondanak az éves parkolási engedélyükről. A dugók, a benzingőz mérséklése minden közlekedő érdeke, így ösztönözzük az alternatív közlekedési eszközök használatát. Belső-Terézvárosban 86 helyen építünk ki mikromobilitási pontokat, azaz a kerékpároknak, rollereknek és robogóknak parkolóhelyeket. Itt kell majd kötelezően elhelyezni az elektromos rollereket is, így ezzel megszűntetjük a sokakat bosszantó rollerkáoszt. Elkezdjük az elektromos töltőállomások kialakításának előkészítését is, és új kerékpártámaszokat is telepítünk.
B13: 2022 | C13: 2022-3.jpg | E13: Biztonságosabb és tisztább közterületek | F13: A kerületi térfigyelő rendszer évek óta elavult. Idén elkezdjük a kamerarendszer modernizálását, amelynek köszönhetően a meglévő 95 helyszín mellett további 45-re helyezünk ki új kamerákat. Ezek segítségével a bűncselekményt vagy az illegális szemétlerakást elkövetőkkel szemben is hatékonyabban tudunk fellépni. A helyi rendőrkapitányságot és a Terézváros Közrendjéért és Közbiztonságáért Alapítványt idén is támogatja az önkormányzat. Ahogy a korábbi években, a köztisztaságra továbbra is kiemelt figyelmet fordítunk. A rendszeres és alapos takarításhoz szükséges források biztosítása mellett további új kukák és csikktartók, új kutyaboxok kihelyezésére is sor kerül idén.
... B19: 2022 | C19: 2022-9.jpg | E19: Mire fordítjuk a legtöbbet 2022-ben? | F19: Reménykedünk, hogy 2022 a nyugodtabb építkezés éve lesz, és nem egy újabb koronavírus-járvány vagy egy európai háború határozza meg az életünket. Egy normális évet szeretnénk, amikor az önkormányzat bevételei olyan ütemben nőnek, mint a 2010-es években, mert így egyszerre válna lehetővé a tartalékképzés és a tervezett fejlesztések végrehajtása mellett az újabbak tervezése, a rászorulóknak járó támogatások további bővítése.
B20: 2023 | C20: 2023-1.jpg | E20: Terézváros 2030 - megújuló utcák, terek | F20: A sok egyeztetéssel járó, hosszú tervezési folyamat után idén elkezdjük felszedni az aszfaltot, indulnak a felújítási munkálatok Terézváros utcáin. Ezzel az elmúlt harminc év legnagyobb közterület-megújítási programját kezdjük megvalósítani. Tavasszal rajtol a Csengery utca felújítása, majd nekilátunk a Bajcsy köz, a Szobi és a Káldy Gyula utca, a Révay köz teljes szakaszának, idén kezd szépülni a Szinyei Merse utca, a Paulay utca, vagy éppen a Ferdinánd rézsű, tovább fejlesztjük a Liszt Ferenc teret. A folyamat végére, 2030-ra nem maradhat egyetlen utca és tér sem, amit valamilyen módon ne tennénk emberléptékűbbé, használhatóbbá, tisztábbá és rendezettebbé. A kerületben ugyanis az alternatív közlekedési lehetőségek javításán, a forgalomcsillapításon, a gyalogos- és zöldfelületek növelésén, valamint a közösségi terek maximalizálásán lesz a hangsúly. | G20: 🚧 Fejlesztések, 🧹 Köztisztaság
B21: 2023 | C21: 2023-2.jpg | E21: Könnyebb parkolás, biztonságosabb közlekedés | F21: Az átmenő forgalmat és a vendégparkolások számát csökkenteni, a terézvárosiak parkolását viszont továbbra is könnyíteni szeretnénk. Belső-Terézvárosban tavaly óta használják az este 6 és reggel 7 közötti időtartamra szóló kizárólagos lakossági parkolóhelyeket, ennek előnyeit pedig idén már a Külső-Terézvárosban élők is élvezhetik. A lakossági parkolási engedéllyel rendelkező lakóknak így ezeken a területeken is könnyebb lesz parkolóhelyhez jutni. Az önkormányzat anyagi hozzájárulásával továbbra is jóval piaci ár alatt juthatnak parkolóházi helyekhez – immár 128-hoz – a helyi lakosok. Tavaly hét, idén már kilenc parkolóházban élhetnek ezzel a lehetőséggel azok a terézvárosiak, akik cserébe lemondanak az éves parkolási engedélyükről, azaz a felszíni parkolóhelyek kedvezményes használatáról. A forgalomcsillapítást és a biztonságot növeli, hogy valamennyi átalakuló utcában kiemeljük a kereszteződéseket, helyenként elhúzzuk a sávokat, lassításra kényszerítve ezzel az autósokat. Sőt, ennél is tovább megyünk: azokon a területeken, ahol nem közlekednek a BKV járművei, bevezetjük a 30 kilométer/órás sebességkorlátozást. A terézvárosi és a fővárosi önkormányzat is alakít ki mobilitási pontokat, Mobikat a kerületben, amelyből összesen 105 darab lesz a folyamat végére. Csak itt lehet majd letenni a kölcsönzött e-rollereket, de lehet majd itt parkolni saját kerékpárral vagy rollerrel is. | G21: 🚧 Fejlesztések, 🚦 Közlekedés
B22: 2023 | C22: 2023-3.jpg | E22: Tisztább, biztonságosabb közterületek | F22: A kerület több pontján megújul a közvilágítás, és idén elkészül az a 140 kamerából álló modern térfigyelő-rendszer, amellyel Terézváros teljes területén, a nap 24 órájában nyomon lehet követni minden eseményt. A megújuló kamerarendszer nem csak a rendőrök munkáját, a bűnelkövetők elfogását segíti, hanem az illegális szemetelőket, de akár a kutyaürüléket hátrahagyókat is könnyebben tetten lehet érni. Bár eddig is kiemelkedő összegből gazdálkodhatott, tovább növeltük a köztisztaságért felelős Terézvárosi Foglalkoztatást Elősegítő Nonprofit Kft. költségvetését. A cél ugyanis az, hogy a közterek soha nem látott gyakorisággal való tisztításával, a rendkívüli takarítások mielőbbi elvégzésével mintakerületet teremtsünk. A köztiszta cégünk megnövelt büdzséjéből jut majd például két új, környezetbarát teherautóra, dolgozói létszámbővítésre, szerelőműhely kialakítására, még gyakoribb utcamosásra, újabb kukák és dogboxok kihelyezésére, a zöldfelületek hatékonyabb kezelésére, és olyan gyorsreagálású csoport megszervezésére, amely a köztisztasági panaszok bejelentésekor azonnal intézkedik. Emellett az eddigieknél nagyobb hangsúlyt fektetnek a köztisztasággal kapcsolatos figyelemfelhívásra, tájékoztatásra, szemléletformálásra is. | G22: 🚧 Fejlesztések, 🛡️ Közbiztonság, 🧹 Köztisztaság
B23: 2023 | C23: 2023-4.jpg | E23: Újjászülető társasházak, zöldülő udvarok | F23: A társasházak felújításához évről évre növeljük a pályázható összeg nagyságát, és folyamatosan bővítjük a pályázati palettát, egyre több munkára lehet támogatást nyerni. Emellett Budapest 150. születésnapja apropóján külön homlokzatfelújítási pályázatot is hirdettünk a társasházaknak, amellyel ugyancsak jelentős összegű támogatást kaphatnak a tulajdonosok az épületek megszépítéséhez. Ahogy korábban, idén is támogatást lehet nyerni egyebek mellett a nyílászárók cseréjéhez, kéménybéleléshez, vagy épp a postaládák cseréjéhez. A zöld pályázatokon nyerhető támogatásokkal a társasházak belső udvarait zöld szigetekké alakíthatják a lakók, hiszen új zöld felületek kialakítására, újabb növények telepítésére, növényfalakra, homlokat befuttatására, növényládák beszerzésére és öntözőrendszer kialakítására, továbbá a kertépítészeti tervek kidolgozására, komposztálóra, padok és kerékpártámaszok telepítésére is lehet támogatást nyerni. Térítésmentesen biztosítjuk a társasházaknak, hogy minősített favizsgáló szakember mérje fel az udvarokon lévő fákat, a Terézvárosi Foglalkozást Elősegítő Nonprofit Kft. pedig elvégezze az ápolási és növény-egészségügyi munkákat. Az Utcakert Programmal az ingatlanok előtti közterület zöldítését segítjük. | G23: 🌱 Zöld, 🚧 Fejlesztések
B24: 2023 | C24: 2023-5.jpg | E24: Terézváros otthont ad | F24: Noha folyamatosan hozzuk rendbe a rossz állapotú, lakhatatlan bérlakásokat, és ezekbe folyamatosan költözhetnek be a bérlőink, még mindig sok kerületi lakos küzd lakhatási gondokkal. Éppen ezért idén is folytatjuk az ingatlanjaink lakhatóvá tételét, így a tervek szerint év végére újabb 30 lakással bővül a kiadható állapotban lévő ingatlanjaink száma. Ezekbe a szociális és szolgálati lakásokba lakhatási problémákkal küzdő terézvárosiak és terézvárosi közintézményekben dolgozók költözhetnek be. Az Aradi utca 22. szám alatt lévő, teljes mértékben saját tulajdonú bérházunk teljes, a pincétől a padlásig történő felújítását tavaly elkezdtük, és idén is folytatjuk. Egyebek mellett megerősítjük a ház alapját, hogy a későbbi extra terheket, például az új födémet elbírja, felújítjuk a külső homlokzatot, kicseréljük a liftet, megújítjuk a ház elektromos hálózatát, felújítjuk az utcai üzlethelyiségeket, a tetőtérben pedig egy új lakást alakítunk ki. | G24: ❤️ Gondoskodás, 🚧 Fejlesztések
B25: 2023 | C25: 2023-6.jpg | E25: Jól karbantartott intézmények | F25: Napjuk jelentős részét oktatási-nevelési intézményben töltik a gyerekek, ezért nagy gondot fordítunk ezek minél korszerűbbé, szebbé, használhatóbbá tételére. A kisebb-nagyobb felújítási, karbantartási munkálatok rendszeresek, de idén tervezzük például a Szív Óvoda tetejének átfogó javítását és szigetelését, több helyen pedig fűtéskorszerűsítést, hőszigetelést, nyílászárócserét végzünk; utóbbit például a Városliget fasori bölcsődénkben. Ebben az évben végezzük el a Kincseskert Óvoda teljes udvarfelújítását, ahogy a Játékvár Óvoda udvarának felújítása is folytatódik. Idén kerül sor a Derkovits Gyula Általános Iskola konyhafelújítására, akadálymentesítjük a Szinyei Merse Pál Gimnázium Kmetty utcai bejáratát. A Terézvárosi Egészségügyi Szolgálat állami átvételét nem támogatjuk, és ahogy korábban, idén is dolgozunk a korszerűsítésén. Jelentős összeget fordítunk egyebek mellett a tűzvédelemre, liftekre, tetőfelújításra. | G25: 🚧 Fejlesztések, 🧸 Óvoda, ❤️ Gondoskodás
B26: 2023 | C26: 2023-7.jpg | E26: Elkezdődhet a Hunyadi téri piac belső felújítása | F26: Csakúgy, mint az utcák, a piac belsejének felújítását is hosszú tervezési folyamat előzte meg, amely során a kereskedelmi, a szolgáltatói és a közösségi szempontokra egyaránt figyelmet fordítottunk. Idén pedig már sor kerülhet a közbeszerzés kiírására. Ha ez sikerrel zárul, az év második felében elkezdődhetnek a munkálatok. Ennek során megtörténik az utólagos hozzáépítések elbontása, a belső területek helyreállítása, egy többfunkciós galéria építése. A Szófia utcai oldalra tervezett teraszok, a környező utcák gyalogosbaráttá, élhetőbbé alakítása is hangsúlyos szerepet kapott a tervekben. | G26: 🚧 Fejlesztések, 🚦 Közlekedés
B27: 2023 | C27: 2023-8.jpg | E27: Széleskörű szociális gondoskodás | F27: Mi vagyunk a legszolidárisabb kerület. A ciklus eleje óta minden évben bővítettük a szociális támogatások körét, növeltük egyes támogatások mértékét, így Budapesten immár mi adjuk a legtöbb támogatást, a legnagyobb összegekkel és a legmagasabb felső jövedelemhatárral. Továbbá egy kerület sem támogatja olyan mértékben az iskolai, óvodai étkeztetést, mint mi. Nem csak a támogatásokra, a szociális intézményeinkre is nagy gondot fordítunk. Ezért bővítjük például idén a Terézvárosi Értelmi Fogyatékosok Napközi Otthonát, az energiatakarékosság jegyében pedig nyílászárókat cserélünk a Terézvárosi Gondozó Szolgálat Benczúr utcai irodájában. Indul az időstaxi: a 60 évnél idősebb terézvárosiak ingyen vehetik igénybe az önkormányzat minibuszát, hogy könnyebben elérjék az egészségügyi intézményeket, a hivatalokat, vagy éppen segítséget kapjanak nagyobb bevásárláskor, bentlakásos szociális intézménybe történő költözéskor. | G27: ❤️ Gondoskodás, 🚦 Közlekedés
B28: 2023 | C28: 2023-9.jpg | D28: 2023.mp4 | E28: Közösségépítő programok | F28: Hiszünk a helyi rendezvények közösségépítő erejében. Hisszük, még otthonosabbá válhat a kerület, ha alkalmat adunk arra, hogy az egymást legfeljebb arcról ismerő szomszédok bemutatkozzanak egymásnak. Soha nem látott mennyiségű és minőségű kulturális rendezvénnyel járulunk hozzá ehhez: sok más mellett idén is lesz TeFeszt, Király-nap, Hunyadi téri programsorozat - például szabadtéri kiállításokkal, kertmozival -, lommentő piac, és természetesen az Eötvös10 programjai, díjmentes tanfolyamai is remek lehetőséget kínálnak ismeretségek, barátságok kötésére. Számos programunk ráadásul ingyenes vagy kedvezménnyel látogatható, mert nem szeretnénk falak közé zárni a kultúrát. Inkább kihozzuk az utcára. | G28: 🎉 Közösség
B29: 2024 | C29: 2024-1.jpg | E29: Terézváros 2030 – megújuló utcák, terek | F29: A Terézváros 2030 program fő célja, hogy hosszú évtizedek után végre megújuljanak a kerület közterületei, méghozzá a közös területeink újragondolásával. A korábbinál nagyobb teret kap a gyalogosközlekedés, a járdák mindenhol jól használhatók, szélesek lesznek. A program hangsúlyos eleme a ,,zöldítés” mellett a forgalomcsillapítás: a kerület valamennyi mellékutcája 30-as övezetbe kerül az év során, és számos kereszteződésben az úttest kiemelése kényszeríti majd lassításra az autókat. A Csengery utca középső része 2024 tavaszára készül el, miközben már megindul a Podmaniczky utca és a Szondi közé eső szakasz felújítása; majd az Aradi és az Andrássy út, illetve a Szófia és a Király utca között dolgoznak. A tavasz derekán lesz esedékes a Nagymező utca útburkolatának cseréje (a Király utcától az Andrássyig), valamint a Bajcsy-Zsilinszky köz sétálóutcává alakítása. A Dessewffy utca (a Bajcsy-Zsilinszky út és a Hajós utca között) az első félévben, a Szondi utca pedig várhatóan az év második felében újul meg a körút és a Vörösmarty utca között. A Terézváros 2030 zöldítési munkái érintik idén a Liszt Ferenc teret (az Andrássy felé eső térrész kerül sorra), a Ferdinánd híd rézsüjét és a Szív utcai teresedést. A forgalomcsillapítást célzó fejlesztések sorában pedig a Szófia–Vörösmarty-kereszteződés mellett átalakulnak a Jókai utca csomópontjai is. | G29: 🚧 Fejlesztések, 🚦 Közlekedés, 🌱 Zöld
B30: 2024 | C30: 2024-2.jpg | E30: Könnyebb parkolás, biztonságosabb közlekedés | F30: Belső-Terézvárosban 2022 óta használják az este 6 és reggel 7 közötti időtartamra szóló kizárólagos lakossági parkolóhelyeket, ennek előnyeit pedig idén már a Külső-Terézvárosban élők is élvezhetik. Továbbra is jóval piaci ár alatt, 50-60 százalékos kedvezménnyel juthatnak parkolóházi helyekhez – immár közel 150-hez – a helyi lakosok. Már tíz parkolóházban élhetnek ezzel a lehetőséggel azok a terézvárosiak, akik cserébe lemondanak az éves parkolási engedélyükről. Idéntől már fizetni kell a parkolásért az Andrássy út Oktogon és Dózsa György út közötti szakaszán, a Kodály köröndön és a Városligeti fasor terézvárosi oldalán is, de a fővárosi önkormányzatnál sikerült elérnünk, hogy a VI. kerületben élők ezeket a fővárosi tulajdonú szakaszokat is ingyen használhassák az éves parkolási engedélyükkel. Valamennyi átalakuló utcában kiemeljük a kereszteződéseket, helyenként elhúzzuk a sávokat, lassításra kényszerítve ezzel az autósokat. A terézvárosi és a fővárosi önkormányzat is alakít ki mobilitási pontokat, Mobikat a kerületben, amelyből összesen 105 darab lesz a folyamat végére. Csak itt lehet majd letenni a kölcsönzött e-rollereket, de lehet majd itt parkolni saját kerékpárral vagy rollerrel is. | G30: 🚦 Közlekedés, 🚧 Fejlesztések, 🛡️ Közbiztonság
B31: 2024 | C31: 2024-3.jpg | E31: Tisztább, biztonságosabb közterületek | F31: Tavaly elkészült a 140 kamerából álló modern térfigyelő-rendszer, amellyel Terézváros teljes területén, a nap 24 órájában nyomon lehet követni minden eseményt. A köztisztaságért felelős Terézvárosi Foglalkoztatást Elősegítő Nonprofit Kft. továbbra is kiemelt összegű büdzséből gazdálkodhat. A cél ugyanis az, hogy a közterek soha nem látott gyakorisággal való tisztításával, a rendkívüli takarítások mielőbbi elvégzésével mintakerületet teremtsünk. Bár a járdák tisztán tartása a társasházak és üzlethelyiség-tulajdonosok feladata, besegítünk nekik. Közel megdupláztuk a hulladékgyűjtő edények számát a kerületben, jelentős béremelést hajtottunk végre a dolgozók körében, a fővárosi területeken is takarítunk, ha szükséges, új eszközöket szereztünk be, létrehoztuk a köztisztasági forródrótot, átalakítottuk a munkarendet, hogy a hétvégi nagyobb terhelés alatt se roppanjon össze a kerület köztisztasága. Az önkormányzat több évtizedes adósságát törlesztettük azzal, hogy felszámoltuk azokat az áldatlan állapotokat, amelyek az Eötvös utca torkolatánál tárolt, az FKF munkájához használt kukáknál állandósultak. Növényzettel befuttatott, zárt és kamerával őrzött konténertárolót alakítottunk ki a Podmaniczky utcában, amelynek a zavartalan működtetését továbbra is garantáljuk. | G31: 🚧 Fejlesztések, 🧹 Köztisztaság, 🌱 Zöld, 🛡️ Közbiztonság
B32: 2024 | C32: 2024-4.jpg | E32: Újjászülető társasházak, zöldülő udvarok | F32: A társasházak felújításához évről évre növeljük a pályázható összeg nagyságát, és folyamatosan bővítjük a pályázati palettát, egyre több munkára lehet támogatást nyerni. Emellett Budapest 150. születésnapja apropóján külön homlokzatfelújítási pályázatot is hirdettünk a társasházaknak, amellyel ugyancsak jelentős összegű támogatást kaphatnak a tulajdonosok az épületek megszépítéséhez. Ahogy korábban, idén is támogatást lehet nyerni egyebek mellett a nyílászárók cseréjéhez, kéménybéleléshez, vagy épp a postaládák cseréjéhez. A zöld pályázatokon nyerhető támogatásokkal a társasházak belső udvarait zöld szigetekké alakíthatják a lakók, hiszen új zöld felületek kialakítására, újabb növények telepítésére, növényfalakra, homlokat befuttatására, növényládák beszerzésére és öntözőrendszer kialakítására, továbbá a kertépítészeti tervek kidolgozására, komposztálóra, padok és kerékpártámaszok telepítésére is lehet támogatást nyerni. Az Utcakert Programmal az ingatlanok előtti közterület zöldítését segítjük. | G32: 🚧 Fejlesztések, 🌱 Zöld
B33: 2024 | C33: 2024-5.jpg | E33: Terézváros otthont ad | F33: Noha folyamatosan hozzuk rendbe a rossz állapotú, lakhatatlan bérlakásokat, és ezekbe folyamatosan költözhetnek be a bérlőink, még mindig sok kerületi lakos küzd lakhatási gondokkal. Éppen ezért idén is folytatjuk az ingatlanjaink lakhatóvá tételét, így a tervek szerint év végére újabb 30 lakással bővül a kiadható állapotban lévő ingatlanjaink száma. Ezekbe a szociális és szolgálati lakásokba lakhatási problémákkal küzdő terézvárosiak és terézvárosi közintézményekben dolgozók költözhetnek be. Az Aradi utca 22. szám alatt lévő, teljes mértékben saját tulajdonú bérházunk teljes, a pincétől a padlásig történő felújításának jelentős részén túl vagyunk, de még zajlanak a munkálatok, egyebek mellett a bérlők ingatlanjait is rendbe tesszük. | G33: ❤️ Gondoskodás, 🚧 Fejlesztések
B34: 2024 | C34: 2024-6.jpg | E34: Jól karbantartott intézmények | F34: Napjuk jelentős részét oktatási-nevelési intézményben töltik a gyerekek, ezért nagy gondot fordítunk ezek minél korszerűbbé, szebbé, használhatóbbá tételére. A kisebb-nagyobb felújítási, karbantartási munkálatok rendszeresek, de idén tervezzük például a Kincseskert óvoda udvarának felújítását, tervben van a Szív óvoda tetőfelújítása, és bár állami feladat lenne, hat iskolában és a Bajza utcai tanuszodában is karbantartási munkálatokat fogunk végezni több, mint 170 millió Ft értékben. A Terézvárosi Egészségügyi Szolgálat állami átvétele egyelőre lekerült a napirendről, ezért ahogy korábban, tovább dolgozunk a korszerűsítésén. A Hunyadi téri piac belső felújításának előkészítése új szakaszba lépett, hamarosan kiírhatjuk a közbeszerzési pályázatot, amely után elkezdődhetnek a munkálatok. Ennek első fázisában az ideiglenes piacot alakítjuk ki az árusoknak, utána indulhat a belső felújítás. | G34: 🎒 Oktatás, 🚧 Fejlesztések, ⚕️ Egészségügy
B35: 2024 | C35: 2024-7.jpg | E35: Az ország legerősebb szociális hálója | F35: Mi vagyunk a legszolidárisabb kerület. A ciklus eleje óta minden évben bővítettük a szociális támogatások körét, növeltük egyes támogatások mértékét, így Budapesten immár mi adjuk a legtöbb támogatást, a legnagyobb összegekkel és a legmagasabb felső jövedelemhatárral. Továbbá egy kerület sem támogatja olyan mértékben az iskolai, óvodai étkeztetést, mint mi. Tavaly indult az Időstaxi-szolgáltatásunk: a 60 évnél idősebb terézvárosiak ingyen vehetik igénybe az önkormányzat minibuszát, hogy könnyebben elérjék az egészségügyi intézményeket, a hivatalokat, vagy éppen segítséget kapjanak nagyobb bevásárláskor, bentlakásos szociális intézménybe történő költözéskor. A szolgáltatás olyannyira népszerűvé vált az idősek körében, hogy idén újabb autót állítunk be ezekre a feladatokra. | G35: ❤️ Gondoskodás, 🎉 Közösség
B36: 2024 | C36: 2024-8.jpg | E36: Párbeszéd mindenhol, mindenkor, mindenkivel | F36: 2019-től alapjaiban kezdtük megújítani önkormányzatunk kommunikációját az egyoldalú tájékoztatásból kilépve a hivatal-lakók közti párbeszéd irányába haladva. Hetente jelentkező hírlevéllel, az ügyintézést segítő tematikus kiadványokkal, angol nyelven is megjelenő magazinnal jelentkezünk 2024-ben is. A hivatali csatornákon kívül a nap 24 órájában fogadjuk és válaszoljuk meg a social media felületeken érkező megkereséseket, és a havi polgármesteri fogadónapokon átlagosan 20-30 helybélinek segítünk személyesen az ügyintézésben, 2024-ben már angol nyelven is a kerületben élő külföldieknek. Idén tovább bővítjük eszköztárunkat: gyarapítjuk a vizuális kommunikációs eszközeinket és social media felületeinket. Folytatjuk az ügyintézési lehetőségek online térbe terelését, és idei tervünk között szerepel egy olyan call center létrehozása, amely tovább egyszerűsíti a terézvárosiak és a hivatal kapcsolatát. | G36: 🎉 Közösség
B37: 2024 | C37: 2024-9.jpg | E37: Közösségépítő programok | F37: Hiszünk a helyi rendezvények közösségépítő erejében. Hisszük, még otthonosabbá válhat a kerület, ha alkalmat adunk arra, hogy az egymást legfeljebb arcról ismerő szomszédok bemutatkozzanak egymásnak. Soha nem látott mennyiségű és minőségű kulturális rendezvénnyel járulunk hozzá ehhez: sok más mellett idén is lesz TeFeszt, Király-nap, Hunyadi téri programsorozat – például szabadtéri kiállításokkal, kertmozival –, lommentő piac, és természetesen az Eötvös10 programjai, díjmentes tanfolyamai is remek lehetőséget kínálnak ismeretségek, barátságok kötésére. Számos programunk ráadásul ingyenes vagy kedvezménnyel látogatható, mert nem szeretnénk falak közé zárni a kultúrát. Inkább kihozzuk az utcára. | G37: 🎉 Közösség
A38: K6406 | B38: 2025 | C38: 2025-1.jpg | E38: Terézváros 2030 – sorra újítjuk fel a közterületeinket | F38: Idén folytatjuk a három éve elindított, átfogó közterület-felújítási programunkat, amellyel évtizedek elmaradását pótoljuk. Sorra szépülnek meg a kerület utcái, terei, társasházai. Ahogy eddig, most is nagyobb teret kap a gyalogosközlekedés, a járdák mindenhol jól használhatók, szélesek lesznek. A zöldítés mellett a program hangsúlyos eleme a forgalomcsillapítás: a mellékutcák 30-as övezetbe sorolása, a kereszteződések kiemelése, a forgalomcsillapító küszöbök elhelyezése. Idén egyebek mellett a Liszt Ferenc tér rekonstrukciója és nyolc új fa elültetése, a Csengery utca utolsó Andrássy-Aradi szakaszának felújítása, a Németh László utca, a Rózsa utca Andrássy út és Király utca közötti szakaszának, valamint a Dessewffy utca Bajcsy-Zsilinszky út és Hajós utca közötti szakaszának megújítása várható. A Zichy utca Jókai utca és Teréz körút közötti szakaszát sétálóutcává alakítjuk, ide fákat ültetünk, és az utcát Kocsis Zoltánról nevezzük el. Előkészítjük a Szondi utca felújítását, az első, Teréz körút és a Vörösmarty utca közötti szakaszának munkálatait pedig idén el is kezdjük. A Kodály köröndre fedett, zöld utasvárókat telepítünk. | G38: 🚧 Fejlesztések
A39: K430402 | B39: 2025 | C39: 2025-2.jpg | E39: Tiszta utcák és zöldterületek | F39: A köztisztaságért felelős Terézvárosi Foglalkoztatást Elősegítő Nonprofit Kft. továbbra is kiemelt összegű büdzséből gazdálkodhat. A köztereket soha nem látott gyakorisággal takarítjuk, a köztisztasági forródrót bevezetésével, majd annak 24 órás bővítésével pedig mintakerületet teremtünk. Bár a járdák tisztán tartása a társasházak és üzlethelyiség-tulajdonosok feladata, besegítünk nekik, csakúgy, mint a fővárosi önkormányzatnak a Teréz körúton, a Bajcsy-Zsilinszky és az Andrássy úton. A kukák feltúrása sok köztisztasági problémával jár, ezért 2025 februárjától a társasházak, vendéglátóhelyek kuka- és szemeteskonténer kihelyezéseit szigorúan ellenőrizzük, és az idősávon túli közterületi tárolásért bírságot szabunk ki. Ugyancsak szigorú bírságra számíthatnak azok a kutyasétáltatók, akik póráz vagy ürülékfelszedésre alkalmas zacskó, chip nélkül sétáltatják a kedvencüket. A bírságokból befolyó összeget köztisztasági feladatok elvégzésére használjuk fel. | G39: 🧹 Köztisztaság
A40: B250103 | B40: 2025 | C40: 2025-3.jpg | E40: Könnyebb, rendezettebb parkolás | F40: A fővárosi önkormányzat hozzájárult ahhoz, hogy 30-ról 40 százalékra növeljük a kizárólagos lakossági parkolóhelyek arányát. Ennek részleteit idén elkezdjük kidolgozni, elindítjuk a tervezési folyamatot. Bővítjük a parkolóházas bérlettel elérhető parkolóhelyek számát is, az eddigi 136 hely mellett további 30 helyen parkolhatnak jóval a piaci ár alatt a terézvárosiak. 2025-től megszüntetjük a helyiek eddigi ingyenes parkolását: 36 ezer forintos éves tarifát vezetünk be az első autókra, a két tonna feletti első autóra pedig 72 ezer forintot kell fizetniük a tulajdonosoknak, üzemeltetőknek. Az intézkedés azon autósok érdekét szolgálja, akiknek tényleg szükségük van az autójukra, nem csak kényelmi okokból vagy megszokásból tartanak fenn autót a belvárosban. Az éves parkolási engedélyekből befolyt pénzt a Terézváros 2030 programra, a kizárólagos lakossági parkolás rendszerének fenntartására, valamint a kedvezményes parkolóházas parkolóhelyek biztosítására fordítjuk. | G40: 🚦 Közlekedés
A41: K7205 | B41: 2025 | C41: 2025-4.jpg | E41: Újjászülető társasházak, zöldülő udvarok | F41: A társasházak felújítását, a homlokzat-felújításokat, az udvarzöldítést az előző évekhez hasonlóan továbbra is nagymértékben támogatjuk. Folyamatosan bővítjük a pályázati palettát, egyre több beruházásra lehet támogatást nyerni. Idén is támogatást biztosítunk egyebek mellett tetőfelújításához, tartószerkezetek vagy éppen a lépcsőház felújításához, víz, gáz vagy elektromos hálózat felújításához, nyílászárók cseréjéhez, kéménybéleléshez, postaládák cseréjéhez. Új elemként került be a belső udvarok felújításának támogatása, és a jövőben azok a társasházak is kaphatnak támogatást, ahol a magánszemélyek tulajdoni hányada nem éri el az 50 százalékot. A zöld pályázatokon nyerhető támogatásokkal a társasházak belső udvarait zöld szigetekké alakíthatják a lakók, hiszen új zöld felületek kialakítására, újabb növények telepítésére, növényfalakra, homlokzat befuttatására, növényládák beszerzésére és öntözőrendszer kialakítására, továbbá a kertépítészeti tervek kidolgozására, komposztálóra, padok és kerékpártámaszok telepítésére is lehet támogatást nyerni. Olyan pályázatot is indítunk, amely közös programok szervezésével a lakóközösségeket erősíti. | G41: 🚧 Fejlesztések, 🎉 Közösség
A42: K6305 | B42: 2025 | C42: 2025-5.jpg | E42: Terézváros otthont ad | F42: Noha megállás nélkül hozzuk rendbe a rossz állapotú, lakhatatlan bérlakásokat, és ezekbe folyamatosan költözhetnek be a bérlőink, még mindig sok kerületi lakos küzd lakhatási gondokkal. Éppen ezért idén is folytatjuk az ingatlanjaink lakhatóvá tételét, így a tervek szerint év végére újabb 25-30 lakással bővül a kiadható állapotban lévő lakásaink száma. Ezekbe a szociális és szolgálati lakásokba lakhatási problémákkal küzdő terézvárosiak és terézvárosi közintézményekben dolgozók költözhetnek be. Folytatjuk az Aradi utca 22. szám alatt lévő, saját tulajdonú bérházunk teljes felújítását. A 63 lakásos házban a munkálatok 2021-ben kezdődtek, és várhatóan 2026-ban fejeződnek be. A VI. kerület egyik legnagyobb önkormányzati projektje ez, hiszen több mint másfél milliárd forintot fordítunk rá. A jövőben krízishelyzetben lévők is igényelhetnek lakást átmeneti időszakra, legfeljebb hat hónapra, amely időszak további hat hónappal majd meghosszabbítható lesz. A Terézvárosi Vagyonkezelő Nonprofit Zrt. egy Eötvös utcai, 263 négyzetméteres ingatlanban tervez krízislakásokat kialakítani. A lakhatási válság enyhítésére az üresen álló magántulajdonú lakásokat is bevonnánk a bérelhető ingatlanok körébe. Ennek koordinálását a fővárosi önkormányzat lakásügynökségéhez való csatlakozással oldjuk meg. | G42: ❤️ Gondoskodás, 🚧 Fejlesztések
A43: K6101 | B43: 2025 | C43: 2025-6.jpeg | E43: Jól karbantartott intézmények | F43: Napjuk jelentős részét oktatási-nevelési intézményben töltik a gyerekek, ezért nagy gondot fordítunk ezek minél korszerűbbé, szebbé, használhatóbbá tételére. A kisebb-nagyobb felújítási, karbantartási munkálatok rendszeresek, idén is gondoskodunk ezekről. Az országban egyedülálló, úgynevezett vertikális, hely híján fölfelé terjeszkedő játszókertet építünk a Bajza Utcai Általános Iskola udvarán. Folytatjuk a Terézvárosi Egészségügyi Szolgálat korszerűsítését, cseréljük a nyílászárókat a gyermekfogászatnál, és hozzálátunk a tüdőgondozó felújításának komplex tervezéséhez is. Ugyancsak javítjuk, újítjuk a siófoki és a dunabogdányi üdülőinket, hogy minél nagyobb biztonság és kényelem fogadja az oda érkező terézvárosiakat. | G43: 🚧 Fejlesztések, 🎒 Oktatás, ⚕️ Egészségügy
A44: K6311 | B44: 2025 | C44: 2025-7.jpeg | E44: Indul a Hunyadi téri vásárcsarnok belső felújítása | F44: A piac teljes felújításon még egyszer sem esett át a megnyitása óta, bár korábban sok kerületvezető tett erre ígéretet. Idén azonban ténylegesen elindul a műemlék épület rekonstrukciója. A munkálatok az ideiglenes piac kialakításával indulnak, és amíg ez június végéig el nem készül, addig a csarnok árusai zavartalanul dolgozhatnak a jelenlegi helyükön. Júliusban elkezdődik a két éves időtartamra tervezett felújítás, amely során a vásárcsarnok teljes belső tere megújul, eltűnnek a középre épített pavilonok, valamint a hozzáépítések. Megépül a piac eredeti terveiben is szerepelt karzat a Szófia utcai részen, míg a másik hosszanti oldalon felújítjuk a műemlék kioszkokat. A homlokzatot több ponton megnyitjuk az utcafront felé.A kialakított galéria kapcsolódhat a földszinti tevékenységekhez, de elkülönülve rendezvénytérként is működhet majd. A felújítás terveit – a műemlék épületek rekonstrukciójáért végzett tevékenységéért Budapestért díjjal is kitüntetett – Archikon építésziroda készítette el. A vásárcsarnokot teljes mértékben önkormányzati forrásból, nettó 2,92 milliárd forintért újítjuk fel. | G44: 🚧 Fejlesztések
A45: K31 | B45: 2025 | C45: 2025-8.jpg | E45: Az ország legsűrűbben szőtt szociális hálója | F45: Mi vagyunk a legszolidárisabb kerület. A ciklus eleje óta minden évben bővítettük a szociális támogatások körét, növeltük egyes támogatások mértékét, így Budapesten immár mi adjuk a legtöbb támogatást, a legnagyobb összegekkel és a legmagasabb felső jövedelemhatárral. Két éve indult az Időstaxi-szolgáltatásunk népszerűsége töretlen, immár két autóval szállítjuk a 60 év felettieket a kért helyszínre. A Terézvárosi Gondozó Szolgálat (Tegosz) idén májustól elindítja a Terézvárosi Támogató Szolgálatot, amely a VI. kerületi fogyatékkal élőket segítheti saját lakókörnyezetükben, illetve mozgásukat, közlekedésüket, önállóságukat biztosítja azzal, hogy – az Időstaxihoz hasonló rendszerben – járművet is biztosít számukra. A támogató szolgálat létrehozására az önkormányzat támogatást nyert el a Fővárosi Szolidaritási Alapból. | G45: ❤️ Gondoskodás
B46: 2025 | C46: 2025-9.jpg | E46: A párbeszéd és a közösség ereje | F46: 2019-től alapjaiban kezdtük megújítani önkormányzatunk kommunikációját, az egyoldalú tájékoztatás helyett az itt élőkkel való párbeszédet választottuk. A hivatali csatornákon kívül fogadjuk és a lehető legrövidebb idő alatt megválaszoljuk a social media felületeken érkező megkereséseket, és a havi polgármesteri fogadónapokon átlagosan 20-30 helybélinek segítünk személyesen az ügyintézésben. Hetente jelentkező hírlevéllel, az ügyintézést segítő tematikus kiadványokkal, angol nyelven is megjelenő magazinnal, az itt élő külföldieknek ingyenesen biztosított magyar nyelvtanfolyammal segítjük a tájékozódást a kerület ügyeiről. Idén egyedülálló eszközzel, közösségi gyűléssel vonjuk be a nőket Terézváros fejlesztésébe. A szakértők által irányított gyűléseken közösen gondolkodhatnak arról, hogyan tehetnénk nőbaráttá, használhatóbbá, egyenjogúbbá a szolgáltatásokat, közterületeket, támogatásokat, programokat. Sok-sok kulturális rendezvénnyel járulunk hozzá a közösségépítéshez: sok más mellett idén is lesz TeFeszt, Király-nap, Hunyadi téri programsorozat, lommentő piac, és természetesen az Eötvös10 programjai, is remek lehetőséget kínálnak ismeretségek, barátságok kötésére. Számos programunk ráadásul ingyenes vagy kedvezménnyel látogatható. | G46: 🎉 Közösség
A47: K6406 | B47: 2026 | C47: 2026-terezvaros2030_1.jpg | E47: Terézváros 2030 – faltól falig megújuló közterületek | F47: A Terézváros 2030 közterület-megújítási programmal évtizedek elmaradásait pótoljuk: sorra újítjuk meg és tesszük barátságosabbá, egyben biztonságosabbá az utcáinkat és tereinket. Az elmúlt évekhez hasonlóan idén is számos változásra számíthatnak a terézvárosiak. A Kármán utca tizenhárom fával, több mint 100 négyzetméter zöldfelülettel, játékokkal, padokkal miniparkként születik újjá. A Révay közt zöldített sétálóutcává alakítjuk át, csakúgy, mint a Kocsis Zoltán utcát, azaz a Zichy Jenő utca Jókai utca és Teréz körút közötti szakaszát. Elkezdődött a Szondi utca megújítása, melynek első, Teréz körút és Csengery utca közötti szakaszát idén adjuk át, és készülnek a tervek a Csengery és a Vörösmarty utca közötti részre, hogy azt 2027-ben sétálóutcává alakítsuk át. Megújul a Paulay Ede utca és a Szív utca egy-egy szakasza, valamint a Lövölde tér egy része is. A program fontos részét képezik a közlekedésbiztonsági fejlesztések, például a csomópont-kiemelések, de az idei tervek között Nagymező utcai gyalogátkelőhelyek kialakítása is szerepel a fővárosi önkormányzattal együttműködve. Elkezdődik az iskolautca terveztetése és engedélyeztetése a Vörösmarty utca Andrássy út és Podmaniczky közötti részén, csakúgy, mint az uniós Egészséges utcák program részeként megújuló Eötvös utcáé a Szondi utca és Podmaniczky utca közötti szakaszon. Az Egészséges utcák program keretében a Szobi utca és Szinyei Merse felújításának terveztetése és engedélyeztetése is elindulhat idén. | G47: 🚧 Felújítások
A48: K430403 | B48: 2026 | C48: 2026-tisztautcak3.jpg | E48: Tiszta utcák, gondosan ápolt zöldfelületek | F48: A közterületeink tisztán és rendezetten tartására továbbra is kiemelt figyelmet fordítunk. Bár a járdák takarítása a társasházak és üzlethelyiségek, cégek feladata, a Terézvárosi Városgondnokság besegít nekik, csakúgy, mint a fővárosi önkormányzatnak egyes fővárosi tulajdonú területeken. Városgondnokságunk nem csak rendkívüli gyakorisággal takarít, forródrótot működtet, hanem a kertészeti és a karbantartási feladatokat is elvégzi. Idén új önként vállalt feladattal tervezik bővíteni a palettát: kísérleti projektként a társasházak kukáit a Városgondnokság munkatársai húznák ki a kukásautó érkezte előtt, és tolják vissza rögtön utána, ezzel csökkentve a szeméttárolók közterületen való kintlétének idejét. A cél az, hogy meggátolják a kukák kiborogatását, a szemét szétszórását. Ehhez először a Király utca – Teréz körút – Nagymező utca – Ó utca – Zichy Jenő utca kukásautó-járaton tesztelik a szolgáltatást. Ezzel párhuzamosan nyáron működik az éjszakai kukakommandó is, a szintén a rendet, tisztaságot hivatott fenntartani. | G48: 🧹 Köztisztaság
A49: K7101,K7205 | B49: 2026 | C49: 2026-tarsashaz2.jpeg | E49: Szépülő társasházak | F49: Az ingatlanok állapotáért mindig a tulajdonosok, azaz a társasházak (vagy vállalkozások) felelnek. A felújítás azonban sokszor komoly anyagi kihívást jelent a lakóközösségeknek, ezért az önkormányzat évről évre jelentős pályázati összegeket biztosít társasházi felújításokra. Mivel az utóbbi időben számottevően nőttek a kivitelezési költségek, idén a korábbinál nagyobb támogatási összegekre lehet pályázni. Egyebek mellett nőtt a fa nyílászárók felújítására adható önkormányzati támogatás összege. Az elmúlt két évben a homlokzatfelújítási programmal 60 ház született újjá, a társasházi felújítási pályázatoknak köszönhetően pedig közel 120 házban végezték el a szükséges helyreállítási munkálatokat. A korszerűsítés, felújítás mellett önkormányzatunk a belső udvarok zöldítését, a növények szakértő ápolását, a kerttervezést is támogatja, és az emberi kapcsolatok erősítéséhez társasházi rendezvények, közös események lebonyolítását is segítjük. | G49: 🚧 Felújítások
A50: K610101,K6205,K6316,K6204 | B50: 2026 | C50: 2026-intezmenyek1.jpg | E50: Karbantartott intézmények | F50: Nagy gondot fordítunk arra, hogy az intézményeinket minél korszerűbbé, szebbé, használhatóbbá tegyük, hiszen a bölcsődékben, óvodákban, iskolákban töltik a gyerekek a napjaik jelentős részét, és a szociális, egészségügyi intézményeinkben is számos terézvárosi lakos fordul meg. A kisebb-nagyobb felújítási, karbantartási munkálatok rendszeresek, ezeket a feladatokat 2026-ban is elvégezzük, ahol pedig szükséges, ott új bútorokat, informatikai vagy egyéb eszközöket szerzünk be a hatékony és akadálytalan működéshez. Idén vehette birtokba a Terézvárosi Család- és Gyermekjóléti Központ (TCSGYK) a Jókai utca 38. alatt új egységét, ahol pszichológiai tanácsadással, családterápiával és fejlesztő foglalkozásokkal segítik a családokat. Idén kezdődik a Szív utcai Óvoda, a Vörösmarty utcai Tüdőgondozó és a Polgármesteri Hivatal felújítása, valamint folytatjuk a Terézvárosi Egészségügyi Szolgálat (TESZ) fejlesztését is. | G50: 🚧 Felújítások, ⚕️ Egészségügy
A51: K6311 | B51: 2026 | C51: 2026-csarnok2.jpeg | E51: Felújítás alatt a Hunyadi téri vásárcsarnok | F51: Az 1897-ben épült piac teljes felújításon még egyszer sem esett át a megnyitása óta, bár korábban sok kerületvezető tett erre ígéretet. Tavaly nyáron azonban ténylegesen elindult a műemlék épület belső rekonstrukciója, amikor a kivitelező hozzákezdett a bontási munkálatokhoz. Idén tavasszal az építési szakaszhoz értek. Készül a könnyűbeton padlózat, kialakítják az új bejáratokat a szállítási útvonalakhoz, valamint a Szófia utcai homlokzaton az üzletek felé, és elkezdődött az erős- és gyengeáramú kábelek védőcsöveinek kialakítása is. A fejépületekben megerősítik a liftek alapozását, a pinceszinten kialakították a vízszigetelést, építik a válaszfalakat, zajlik az aljzatbetonozás. Ebben az évben elvégzik a vásárcsarnokban a fém-, fa-, kő-, és szilikátfelületeket érintő szakrestaurátori munkákat. A tervek szerint a munka 2027-ben fejeződik be. | G51: 🚧 Felújítások
A52: K6305,K5104 | B52: 2026 | C52: 2026-otthon2.jpg | E52: Terézváros otthont ad | F52: Budapesten sokan küzdenek lakhatási nehézségekkel a magas albérleti és lakásárak miatt. Ez Terézvárosban is érezhető, sokan pályáznak önkormányzati bérleményre, ezért az elmúlt évek gyakorlatának megfelelően idén is folytatjuk a rossz állapotú, idáig lakhatásra alkalmatlan ingatlanok lakhatóvá tételét. 2026-ban 20 ilyen ingatlannal tervezzük bővíteni a bérbe adható lakások számát. A szociális és szolgálati lakásokba lakhatási problémákkal küzdő terézvárosiak és terézvárosi közintézményekben dolgozók költözhetnek be. Ebben az évben befejezzük az Aradi 22. szám alatti 63 lakásos, két udvart is magában foglaló, teljes mértékben önkormányzati tulajdonú társasház pincétől a padlásig történő felújítását. Ez az egyik legnagyobb önkormányzati projekt, hiszen a 2021-ben kezdődött munkálatokra több, mint másfél milliárd forintot fordítottunk. Két védett lakást, „női óvóhelyet” is kialakítunk azoknak a nőknek, akik bántalmazó kapcsolatból menekülve kénytelenek elhagyni az otthonukat. A kerületek sorában elsőként csatlakoztunk a Fővárosi Lakásügynökséghez, hogy Budapesten ne egymástól elszigetelten próbáljunk enyhíteni a lakhatási válságon, hanem összefogva segítsünk megfizethető otthonokat teremteni. Adókedvezménnyel támogatjuk a lakások hosszú távú bérbadását, szolgálati lakások biztosításával pedig a kerületünkben/kerületünkért dolgozó kiváló munkaerő megtartása a cél. | G52: ❤️ Gondoskodás, 🚧 Felújítások
A53: K31,K32 | B53: 2026 | C53: 2026-szocialis1.JPG | E53: A legsűrűbben szőtt szociális háló | F53: Továbbra is mi vagyunk a legszolidárisabb kerület. Ahogy a korábbi években, az idei évre is bővítettük a szociális támogatások körét, növeltük egyes támogatások mértékét, így még mindig mi adjuk Budapesten a legtöbb támogatást a legnagyobb összegekkel és a legmagasabb felső jövedelemhatárral. Nem csak kijjebb toltuk a jövedelemhatárokat, hanem egyszerűsítettük is: a 21 eddigi kategória helyett ezentúl csupán hárommal kell számolni. A támogatások sora hosszú, hiszen a szokványos szociális támogatási formák mellett a fiatalok életkezdési támogatásától és az intim csomag támogatástól kezdve a lakásfelújítási támogatáson vagy a 100 évet betöltöttek támogatásán át a hallókészülék vásárlásához nyújtott támogatásig sok mindenben számíthatnak a terézvárosiak önkormányzatunkra. Ezek között megdupláztuk például a nyelvvizsga-felkészülést segítő támogatást, jelentősen emelkedett a „B” kategóriás jogosítvány megszerzéséhez nyújtott hozzájárulás, csakúgy, mint a kerékpáros közlekedés támogatása. Ettől az évtől támogatást nyújtunk a lakások akadálymentesítéséhez. Az ortopéd cipőhöz és szemüveghez pedig idéntől pályázati eljárás helyett szociális támogatás formájában lehet hozzájutni. | G53: ❤️ Gondoskodás
A54: K430501 | B54: 2026 | C54: 2026-kulturalis2.jpg | E54: Kulturális és közösségi programok | F54: A kultúra nem lehet kevesek kiváltsága, ezért kötelességünknek tartjuk, hogy mindenki számára hozzáférhetővé tegyük a kulturális eseményeket. Ezt szolgálja az Eötvös10 művelődési házunk számos ingyenes programja, közterületi rendezvényeink, kiállításaink, és ezért biztosítunk időről-időre ingyenes színházi előadásokat a terézvárosiaknak. Az Eötvös10 együttműködő partnere a Radnóti Színháznak a 2025/2026-os és az azt követő évadban. Évadonként 2-2 színházi előadás az Eötvös10 színpadain látható, az E10 erre a két évadra a színház külső játszóhelyévé avanzsál. Folytatjuk a Budapest Film Zrt.-vel való együttműködést is: 2026 nyarán a Művész Mozi havonta egy ingyenes vetítéssel várja a kerületieket, az év második felében pedig féláron látogathatják az előadásokat a terézvárosi lakcímkártyával rendelkezők. Idén lesz 150 éve annak, hogy átadták az Andrássy utat, amely apropóján a fővárosi önkormányzattal olyan eseménysorozatot tervezünk, amelynek résztvevői lesznek a kerületben található színházak, múzeumok is. 2026-ban megvalósítjuk a női közösségi gyűlés által elfogadott fejlesztési javaslatokat, programokat, de támogatjuk a közösségek erősítését azzal is, hogy a társasházak idén is pályázhatnak támogatásra a közösségi programjaik megrendezéséhez. | G54: 🎉 Közösség
A55: K41 | B55: 2026 | C55: 2026-grafikon_koltsegvetes_priosv2.jpg | E55: +1: szolidaritási adó változásáról lesz egy kép | F55: szolidaritási adó leírása | G55: 🎉 Közösség

Sheet functions
A1: id | B1: name | C1: parent
A2: 107054 | B2: Családsegítés | C2: 1070
A3: 107014 | B3: Támogatott lakhatás hajléktalan személyek részére | C3: 1070
A4: 900070 | B4: Fejezeti és általános tartalékok elszámolása | C4: 9000
A5: 11220 | B5: Adó-, vám- és jövedéki igazgatás | C5: 112
A6: 84070 | B6: A fiatalok társadalmi integrációját segítő struktúra, szakmai szolgáltatások fejlesztése, működtetése | C6: 840
A7: 104060 | B7: A gyermekek, fiatalok és családok életminőségét javító programok | C7: 1040
A8: 104070 | B8: A gyermeki jogok érvényre juttatásával összefüggő feladatok | C8: 1040
A9: 13110 | B9: A közszolgálat egyetemes humánerő-gazdálkodása | C9: 131
A10: 91240 | B10: Alapfokú művészetoktatás | C10: 912
A11: 91250 | B11: Alapfokú művészetoktatással összefüggő működtetési feladatok | C11: 912
A12: 140 | B12: Alapkutatás | C12: 1
... A51: 33020 | B51: Bírósági tevékenység | C51: 330
A52: 104045 | B52: Család-és gyermekjóléti Központ (iskolai szociális munka) | C52: 1040
A53: 104044 | B53: Biztos Kezdet Gyerekház | C53: 1040
A54: 31060 | B54: Bűnmegelőzés | C54: 310
A55: 340 | B55: Büntetés-végrehajtási tevékenységek | C55: 3
A56: 34020 | B56: Büntetés-végrehajtási tevékenységek | C56: 340
A57: 34010 | B57: Büntetés-végrehajtási tevékenység igazgatása | C57: 340
A58: 41150 | B58: Cégnyilvántartás | C58: 411
A59: 84031 | B59: Civil szervezetek működési támogatása | C59: 840
A60: 84032 | B60: Civil szervezetek programtámogatása | C60: 840
A61: 1040 | B61: Család és gyermekek | C61: 10
A62: 104043 | B62: Család-és Gyermekjóléti Központ | C62: 1040
A63: 104042 | B63: Család és gyermekjóléti szolgáltatások | C63: 1040
A64: 74031 | B64: Család és nővédelmi egészségügyi gondozás | C64: 740
... A556: 10 | B556: Szociális védelem | C556: 0
A557: 72220 | B557: Járóbetegek rehabilitációs szakellátása | C557: 722

Sheet kgr
A1: codes
A2: K1
A3: K11
A4: K12
A5: K1201
A6: K1202
A7: K1203
A8: K13
A9: K1301
A10: K130101
A11: K130102
A12: K130103
... A122: K801
A123: B1 | B123: Működési célú támogatások államháztartáson belülről
A124: B1101 | B124: Önkormányzatok működésének általános támogatása
A125: B110101 | B125: Önkormányzati Hivatal működésének állami támogatása
A126: B110102 | B126: Településüzemeltetés - zöldterület-gazdálkodás állami támogatása
A127: B110103 | B127: Településüzemeltetés - közutak állami támogatása
A128: B110104 | B128: Egyéb önkormányzati feladatok állami támogatása
A129: B110105 | B129: A 10 000 lakos feletti önkormányzatok energia áremelkedés miatti támogatása
A130: B1102 | B130: Önkormányzatok egyes köznevelési feladatainak támogatása
A131: B110201 | B131: Óvodaműködtetési támogatás
A132: B110202 | B132: Az óvodákban foglalkoztatott pedagógusok átlagbéralapú támogatása
A133: B110203 | B133: Kiegészítő támogatás a pedagógusok és a pedagógus szakképzettséggel rendelkező segítők minősítéséből adódó többletkiadásokhoz
A134: B110204 | B134: Nemzetiségi pótlék
... A189: B41 | B189: Ingatlanok értékesítése
A190: B42
A191: B43
A192: B44 | B192: Felhalmozási célú átvett pénzeszközök (társasházak)
A193: B4401 | B193: Felhalmozási célú visszatérítendő támogatások, kölcsönök visszatérülése államháztartáson kívülről
A194: B4402 | B194: FELHALMOZÁSI C.TÁMOGATÁSOK ÁLL.-ON Kívülről
A195: B4403 | B195: Felhalmozási c.visszatérítendő tám.,kölcsönök
A196: B4404 | B196: Felhalmozási c. átvett pénzeszközök ( áht-on kívülről , társasházak )
A197: B45
A198: B5 | B198: Finanszírozási bevételek
A199: B6 | B199: Működési célú átvett pénzeszközök
A200: B51 | B200: Belföldi értékpapírok bevételei
A201: B52 | B201: Maradvány igénybevétele
A202: B53 | B202: Államháztartáson belüli megelőlegezések
A203: K44020104
A204: K44020105
A205: K44020106
A206: K44020107
A207: K44020108
A208: K44020109
A209: K44020110
A210: K44020111
A211: K5201
A212: K5202
A213: K6502
A214: K6503
... A222: B12

Sheet tooltips 2026
A1: Azon. | B1: Megnevezés | C1: Súgószöveg
A2: K1 | B2: Személyi juttatások és járulékok | C2: Személyi kiadások és a munkáltató által fizetett járulékaik
A3: K2 | B3: Dologi kiadások | C3: A mindennapi működéshez, a feladatok ellátásához szükséges kiadások
A4: K3 | B4: Ellátottak pénzbeli juttatásai | C4: Az önkormányzat szociális támogatásai. A széleskörű támogatási rendszerben vannak havi rendszerességgel és eseti jelleggel nyújtott támogatások is. A szociális juttatások legnagyobb tételei: az idősek világnapjára adott juttatás, az eseti támogatás, a lakhatási támogatás, a fűtéstámogatás és a gyógyszertámogatás.
A5: K4 | B5: Egyéb működési célú kiadások | C5: Az önkormányzati cégeknek, iskolai alapítványoknak, civil szervezeteknek, kerületi rendőrkapitányságnak nyújtott támogatások.
A6: K6 | B6: Felújítások | C6: Oktatási, egészségügyi intézmények felújítása, közterületek felújítása, önkormányzati lakások felújítása, járda- és útfelújítás
A7: K8 | B7: Finanszírozási kiadások | C7: Számviteli jellegű tétel (korábbi megelőlegzések visszafizetése).
A8: K11 | B8: Önkormányzat személyi juttatásai és járulékai | C8: Személyi kiadások és a munkáltató által fizetett járulékaik
A9: K5 | B9: Beruházások | C9: Az önkormányzat és intézményei (például óvodák, bölcsődék, szociális és egészségügyi intézmények) eszközbeszerzései, lakásállomány bővítése
A10: K7 | B10: Egyéb felhalmozási kiadások | C10: Társasházak felújítására, zöldfelületek fejlesztésére elkülönített összeg
A11: K12 | B11: Polgármesteri Hivatal személyi juttatásai és járulékai | C11: Személyi kiadások és a munkáltató által fizetett járulékaik
A12: K13 | B12: Óvodák személyi juttatásai és járulékai | C12: Személyi kiadások és a munkáltató által fizetett járulékaik
... A23: K54 | B23: Óvodák beruházásai | C23: Kerti eszközök, bútorok, játékok beszerzése
A24: K55 | B24: Terézvárosi Egészségügyi Szolgálat beruházásai
A25: K56 | B25: Terézvárosi Értelmi Fogyatékosok Napközi Otthona beruházásai
A26: K74 | B26: Felhalmozási céltartalék | C26: Fejlesztésekre, felújításokra, beszerzésekre elkülönített tartalék
A27: K1203 | B27: Munkaadókat terhelő járulékok és szociális hozzájárulási adó
A28: K1202 | B28: Külső személyi juttatások | C28: Feladatot ellátó, nem foglalkoztatotti viszonyban lévő személyek juttatásai
A29: K1401 | B29: Foglalkoztatottak személyi juttatásai | C29: Foglalkoztatotti viszonyban lévők személyi juttatásai.
A30: K2105 | B30: Különféle befizetések és dologi kiadások | C30: Legnagyobb tétele az önkormányzat által kifizetett áfa
A31: K2104 | B31: Kiküldetés
A32: K2201 | B32: Készletbeszerzés | C32: Működtetéshez szükséges eszközök, például nyomtatványok, irodaszerek beszerzésére fordított összeg
A33: K2202 | B33: Kommunikációs szolgáltatások | C33: Távközlési díjak (internet, telefon), honlapfejlesztés, videókészítés
A34: K2203 | B34: Szolgáltatási kiadások | C34: A dologi kiadások tetemes részét szolgáltatások vásárlására költi az önkormányzat. Ilyenek például: lakóépületek karbantartása, közös költség fizetés, étkeztetés, bérleti jogviszony megváltása
A35: K2205 | B35: Különféle befizetések és dologi kiadások | C35: Legnagyobb tétele az önkormányzat által kifizetett áfa
A36: K2301 | B36: Fasori óvoda dologi kiadásai | C36: A mindennapi működéshez, a feladatok ellátásához szükséges kiadások
A37: K2302 | B37: Játékvár óvoda dologi kiadásai | C37: A mindennapi működéshez, a feladatok ellátásához szükséges kiadások
A38: K2303 | B38: Szív óvoda dologi kiadásai | C38: A mindennapi működéshez, a feladatok ellátásához szükséges kiadások
A39: K2304 | B39: Mesevilág óvoda dologi kiadásai | C39: A mindennapi működéshez, a feladatok ellátásához szükséges kiadások
A40: K2305 | B40: Kincseskert óvoda dologi kiadásai | C40: A mindennapi működéshez, a feladatok ellátásához szükséges kiadások
A41: K4401 | B41: Általános tartalék | C41: Nem konkrét célokra, hanem a gazdálkodás biztonsága érdekében nem várt kiadásokra félretett tartalék.
A42: K4402 | B42: Céltartalék | C42: Bérkiegészítésekre, kitüntetésekre, óvodai, iskolai támogatásokra, szociális és egyéb támogatásokra szolgáló tartalék
A43: K5104 | B43: Ingatlanvásárlás | C43: Ingatlangyarapítás a lakhatási válság enyhítésére
... A47: K130202 | B47: Külső személyi juttatások | C47: Feladatot ellátó, nem foglalkoztatotti viszonyban lévő személyek juttatásai
A48: K130203 | B48: Munkaadókat terhelő járulékok és szociális hozzájárulási adó
A49: K130301 | B49: Foglalkoztatottak személyi juttatásai | C49: Foglalkoztatotti viszonyban lévők személyi juttatásai.
A50: K130302 | B50: Külső személyi juttatások | C50: Feladatot ellátó, nem foglalkoztatotti viszonyban lévő személyek juttatásai
A51: K130303 | B51: Munkaadókat terhelő járulékok és szociális hozzájárulási adó
A52: K130401 | B52: Foglalkoztatottak személyi juttatásai | C52: Foglalkoztatotti viszonyban lévők személyi juttatásai.
A53: K130402 | B53: Külső személyi juttatások | C53: Feladatot ellátó, nem foglalkoztatotti viszonyban lévő személyek juttatásai
A54: B1 | B54: Működési célú támogatások államháztartáson belülről | C54: Döntően a központi költségvetésből kapott, normatív alapon járó, feladatfinanszírozási és kiegészítő támogatások
A55: B2 | B55: Közhatalmi bevételek | C55: A lakosok és a helyi vállalatok által befizetett helyi adók, díjak, bírságok
A56: B3 | B56: Működési bevételek és átvett pénzeszközök | C56: Olyan működéshez köthető bevételek, amelyek nem tartoznak a támogatások, az adóbevételek közé, és nem értékesítésből származnak (például parkolási bevételek, az üzlethelységek, lakások bérleti díja, járóbeteg-ellátáshoz kapott központi támogatás).
A57: B4 | B57: Felhalmozási bevételek, támogatások, átvett pénzeszközök | C57: Ingatlanok értékesítése, fejlesztésre kapott állami támogatások, nyújtott kölcsönök visszatérülése.
A58: B5 | B58: Finanszírozási bevételek | C58: Az előző évi maradványok, lejárt betétekből származó bevétel.
A59: B11 | B59: Önkormányzat központi működési támogatásai | C59: Döntően a központi költségvetésből a napi működés kötelező feladataira kapott, kötött felhasználású támogatások
A60: B12 | B60: Egyéb működési célú támogatások bevételei államháztartáson belülről | C60: A Nemzeti Egészségbiztosítási Alapkezelőtől (NEAK) egészségügyi és szociális feladatok ellátására érkező összeg. Ez az összeg a Terézvárosi Egészségügyi Szolgálat és a Terézvárosi Gondozó Szolgálat bevételeinek egy részét képezi.
A61: B21 | B61: Vagyoni típusú adók
A62: B22 | B62: Iparűzési adó | C62: Az iparűzési adót a vállalkozások az önkormányzatnak fizetik be, Budapesten a fővárosi önkormányzatnak. Budapesten a befolyt teljes iparűzési adó bevétel 54%-a a fővárosi önkormányzaté, a maradék 46%-on pedig a kerületek osztoznak előre rögzített %-ok alapján, melyet a 26. évi CXXXIII. törvény rögzít. Minél több vállalkozás fizet Budapesten iparűzési adót, annál több lesz adott kerület iparűzési adó bevétele. A kerület iparűzési adó bevétele nem függ attól, hogy adott nagyvállalatnak abban a kerületben van-e a székhelye.
A63: B23 | B63: Gépjárműadó | C63: A kormány intézkedése szerint 2022 óta nem önkormányzati bevétel.
A64: B24 | B64: Idegenforgalmi adó | C64: Helyi adó, amelyet a kerületben eltöltött vendégéjszakák után személyenként kell megfizetni
A65: B25 | B65: Egyéb közhatalmi bevételek (díjak, bírságok, közterület átengedése ) | C65: A bevételi kategória jelentős része a közterülethasználati díj, azaz a vendéglátó helyek teraszai, építkezésekhez használt közterület után fizetendő díj.
A66: B31 | B66: Nyújtott szolgáltatás ellenértéke | C66: Nyújtott szolgáltatásokért elsősorban a költségvetési szervek tesznek szert bevételre. Így jut bevételhez például a Terézvárosi Egészségügyi Szolgálat a díjköteles egészségügyi szolgáltatásokért.
A67: B32 | B67: Közvetített szolgáltatások ellenértéke | C67: A közvetített szolgáltatásokért jellemzően a Belső-Pesti Tankerületi Központ fizet az önkormányzatnak
A68: B33 | B68: Tulajdonosi bevételek | C68: Parkolásüzemeltetésből, lakások és helyiségek bérleti díjából, közterülethasználati díjból származó önkormányzati bevételek
A69: B34 | B69: Ellátási díjak | C69: Bölcsődékben, óvodákban, iskolákban az étkezésért fizetett díjakból származó bevételek. Az étkezésért az azt igénybe vevők kb. 6%-a fizet, a többiek ingyenesen vagy kedvezményesen étkeznek.
A70: B35 | B70: Kiszámlázott általános forgalmi adó | C70: A tulajdonosi bevételek (például helyiség-bérbeadásból származó bevételek) áfája
A71: B36 | B71: Általános forgalmi adó visszatérítése | C71: Az önkormányzati áfás kiadások után visszaigényelhető összeg (például étkeztetés, közüzemi díjak áfája esetében)
A72: B37 | B72: Kamatbevételek | C72: Az államkötvényben tartott befektetésekből származó kamatbevételek
A73: B38 | B73: Egyéb működési bevételek | C73: Késedelmi kamatokból származó bevétel (ingatlanbérleti díjak után)
... A85: B2102 | B85: Telekadó | C85: A telekadót a Terézvárosban lévő telek, azaz épülettel, épületrésszel be nem épített földterület után kell fizetni. A telekadó alapját a telek m2-ben számított területe adja.
A86: B2501 | B86: Közterület-használat, parkolás
A87: B2502 | B87: Bírságok, díjak
A88: B110102 | B88: Településüzemeltetés - zöldterület-gazdálkodás állami támogatása | C88: A központi költségvetésből a településüzemeltetés támogatása
A89: B110201 | B89: Óvodaműködtetési támogatás | C89: Központi költségvetésből az óvodák működtetésének támogatása
A90: B110202 | B90: Az óvodákban foglalkoztatott pedagógusok átlagbéralapú támogatása | C90: Központi költségvetésből az óvodák működtetésének támogatása
A91: B110203 | B91: Kiegészítő támogatás a pedagógusok és a pedagógus szakképzettséggel rendelkező segítők minősítéséből adódó többletkiadásokhoz | C91: Központi költségvetésből az óvodák működtetésének támogatása
A92: B110204 | B92: Nemzetiségi pótlék
A93: B110205 | B93: Az óvodákban foglalkoztatott pedagógusok nevelőmunkáját közvetlenül segítők átlagbéralapú támogatása
A94: B250101 | B94: Közterület-használat átengedése
A95: B11030101 | B95: Bölcsőde, mini bölcsőde támogatása | C95: A központi költségvetésből a bölcsődei bértámogatás és az üzemeltetés támogatása
A96: B11030103 | B96: Egyes szociális és gyermekjóléti feladatok támogatása | C96: A központi költségvetésből a család- és gyermekjóléti szolgálat, a házi segítségnyújtás, fogyatékosok nappali ellátásának támogatása
A97: K21 | B97: Önkormányzat dologi kiadásai | C97: A mindennapi működéshez, a feladatok ellátásához szükséges kiadások
A98: K24 | B98: Terézvárosi Egészségügyi Szolgálat dologi kiadásai | C98: A mindennapi működéshez, a feladatok ellátásához szükséges kiadások
A99: K25 | B99: Terézvárosi Értelmi Fogyatékosok Napközi Otthona dologi kiadásai | C99: A mindennapi működéshez, a feladatok ellátásához szükséges kiadások
A100: K26 | B100: Terézvárosi Gondozó Szolgálat dologi kiadásai | C100: A mindennapi működéshez, a feladatok ellátásához szükséges kiadások
A101: K27 | B101: Terézvárosi Család- és Gyermekjóléti Központ dologi kiadásai | C101: A mindennapi működéshez, a feladatok ellátásához szükséges kiadások
A102: K28 | B102: Terézvárosi Egyesített Bölcsődék dologi kiadásai | C102: A mindennapi működéshez, a feladatok ellátásához szükséges kiadások
A103: K18 | B103: Terézvárosi Egyesített Bölcsődék személyi juttatásai és járulékai | C103: Személyi kiadások és a munkáltató által fizetett járulékaik
A104: K57 | B104: Terézvárosi Gondozó Szolgálat beruházásai
A105: K59 | B105: Terézvárosi Egyesített Bölcsődék beruházásai
A106: K62 | B106: Egészségügyi intézmények felújításai | C106: Az egészségügyi intézmények felújítási kiadásai
A107: K63 | B107: Egyéb intézmények, épületek felújítása | C107: Hivatali intézmények felújítása, térfelújítás, önkormányzati lakások felújítása, kutyafuttató-felújítás, járda- és útszakasz felújítás
A108: K64 | B108: Közterek felújítása | C108: Közterek felújítása, közterek zöldítése, kutyafuttató-felújítás, járda- és útszakasz felújítás, forgalomcsökkentés
A109: K72 | B109: Egyéb felhalmozási célú támogatások államháztartáson kívülre
A110: K1103 | B110: Munkaadókat terhelő járulékok és szociális hozzájárulási adó
A111: K1201 | B111: Foglalkoztatottak személyi juttatásai | C111: Foglalkoztatotti viszonyban lévők személyi juttatásai.
A112: K1301 | B112: Fasori óvoda személyi juttatásai és járulékai | C112: Személyi kiadások és a munkáltató által fizetett járulékaik
A113: K1302 | B113: Játékvár óvoda személyi juttatásai és járulékai | C113: Személyi kiadások és a munkáltató által fizetett járulékaik.
A114: K1303 | B114: Szív óvoda személyi juttatásai és járulékai | C114: Személyi kiadások és a munkáltató által fizetett járulékaik.
A115: K1304 | B115: Mesevilág óvoda személyi juttatásai és járulékai | C115: Személyi kiadások és a munkáltató által fizetett járulékaik
A116: K1305 | B116: Kincseskert óvoda személyi juttatásai és járulékai | C116: Személyi kiadások és a munkáltató által fizetett járulékaik,
A117: K1402 | B117: Külső személyi juttatások | C117: Feladatot ellátó, nem foglalkoztatotti viszonyban lévő személyek juttatásai
A118: K1403 | B118: Munkaadókat terhelő járulékok és szociális hozzájárulási adó
A119: K1501 | B119: Foglalkoztatottak személyi juttatásai | C119: Foglalkoztatotti viszonyban lévők személyi juttatásai.
A120: K1502 | B120: Külső személyi juttatások | C120: Feladatot ellátó, nem foglalkoztatotti viszonyban lévő személyek juttatásai
A121: K1503 | B121: Munkaadókat terhelő járulékok és szociális hozzájárulási adó
A122: K1601 | B122: Foglalkoztatottak személyi juttatásai | C122: Foglalkoztatotti viszonyban lévők személyi juttatásai.
A123: K1602 | B123: Külső személyi juttatások | C123: Feladatot ellátó, nem foglalkoztatotti viszonyban lévő személyek juttatásai
A124: K1603 | B124: Munkaadókat terhelő járulékok és szociális hozzájárulási adó
...
